[
  {
    "corp_code": "00126380",
    "company_name": "삼성전자(주)",
    "memo": "관심을 위한 매수\n자본집약적 사업 + ROIC > WACC의 지속성이 의심, 사이클주라는 점 때문에 엄청난 해자를 가진 기업은 맞지만, 좀 더 성장성 높은 기업에 투자하고 싶은 마음이 있다.\n\n글로벌에서 반도체의 거의 핵심 기업이기 때문에 관심 / 관찰을 위한 소량 매수만 진행",
    "memo_updated_at": "2026-01-26T02:26:35.769131+00:00"
  },
  {
    "corp_code": "01747977",
    "company_name": "(주)엘케이켐",
    "memo": "반도체 공정 산업\n토스에서 단기 과열이길래 찾아봄\n지표가 좋고 공격적 재투자 기업인데 최근에 갑자기 투자자들이 몰림\n판매처는 주로 국내\n일단 관찰 2025년에도 재투자한것만큼 매출, FCF등 건전해지면 매수 고려",
    "memo_updated_at": "2026-01-08T23:57:42.866844+00:00"
  },
  {
    "corp_code": "00139834",
    "company_name": "(주)엘지씨엔에스",
    "memo": "클라우드 산업. 주 매출이 내수인 기업이다.\n특징 중 눈에 띈 부분은 발행 주식 수를 늘리지 않음. -> 기존 주주 희석은 발생하지 않으나, 내 개인적인 생각에 성장에 한계를 느끼고 있다고 생각함.\n전산장비, 외주용역비가 주 원재료이며 2024년 사업보고서에 기재된 해당 비용은 3조임.\n한국 기업 클라우드 주 사용처를 알아보니 아마존, 마이크로소프트가 압도적이고,\n국내 기업에서는 삼성 SDS가 1등이라고 함.\n경쟁사 해자로써는 의심이 든다.\n지표 자체는 좋지만 내수 중심인 만큼 성장세에 대한 우려가 있다.\n\n성장성, 해자, 클라우드 서비스를 빌려 인력을 통해 서비스 제공을 한다라는점은 있지만\n지표가 워낙 좋고 안정적인 기업이라는건 장점.\n하지만 클라우드를 직접 개발하는것이 아니라, 이미 만들어진 클라우드를 유통하는 구조.\n가격결정권이 없으며, 투하자본대비이익율이 좋은것도 해당 이유.\n장기적 투자 관점으로 봤을 땐 성장기대치가 낮아보여 매수하지않음.\n\n\n",
    "memo_updated_at": null
  },
  {
    "corp_code": "00863533",
    "company_name": "(주)삼양엔씨켐",
    "memo": "PR 소재 생산 기업\nPR분야는 일본이 먹고 있고, 해당 기업도 대부분 일본에서 가져온 PR을 검사하는 일을 한다.\n부채가 상당히 많았는데 최근에 매출을 늘리며 거의 갚는 모습을 보여줬다. -> 가산점\n그에 이어 작년에 다시 단기차입금을 더 받아 CAPEX를 늘리는 등 공격적인 운영을 보여주고 있음.\n극복해나가는 과정이 마음에 드는데 가격 자체가 저렴하진 않다. 미래 가치창출이 올라갈거라고 예상하지만 시장도 같이 예상하는 듯 함(PER 20배 물론 반도체 관련 미래 기술이라 프리미엄 가능성 있음)\n마음이 간다.. 부채를 많이 빌리고 재투자, 그걸 갚아나가는 능력을 봤을 때 성장 기대성이 높다고 판단됨.\n지표 자체도 매 년 올라오고있는점도 가산점.\n\n하지만 매수하기에는 아직 부족해보인다 관찰로 분류\n2025년 사업보고서에서도 개선된 모습 보인다면 매수\n\n",
    "memo_updated_at": null
  },
  {
    "corp_code": "01590528",
    "company_name": "(주)아스테라시스",
    "memo": "피부 미용 시술쪽은 생활에 필수품은 아니다\n수요가 정해져있어 크게 성장하기 어렵다고 판단.",
    "memo_updated_at": "2026-01-08T21:06:58.091609+00:00"
  },
  {
    "corp_code": "01718407",
    "company_name": "주식회사 블랙야크아이앤씨",
    "memo": "산업 현장용 PPE(안전화, 안전복, 산업안전용품) 만드는 기업\n사업 모델이 성장에 한계가 있다고 생각함\n",
    "memo_updated_at": "2026-01-08T21:13:52.993597+00:00"
  },
  {
    "corp_code": "00867034",
    "company_name": "(주)듀켐바이오",
    "memo": "비전이 있어보이나 매출액 자체가 늘고있지 않음",
    "memo_updated_at": "2026-01-08T21:28:44.154722+00:00"
  },
  {
    "corp_code": "01519790",
    "company_name": "주식회사 엠앤씨솔루션",
    "memo": "방산산업은 정부의 제약이 많은 편이라 한계가 있다고 생각함",
    "memo_updated_at": "2026-01-08T21:32:10.851970+00:00"
  },
  {
    "corp_code": "01016309",
    "company_name": "(주)한켐",
    "memo": "OLED 유기화합물 소재가 매출 90퍼센트\n판매처는 국내 거의 100%\n영업조직을 통한 매출처 발굴을 하지 않고, 기술에 집중하는편.\n내 판단에는 좀 수동적인 느낌이 난다.\n이 회사의 기술력이 원탑이라 OLED 수주가 알아서 찾아오면 문제 없이 성장하겠지만, 그렇지 않다면 정체된다는 말이니 해당 산업에 점유율이 어느정도인지 파악 필요.\n같은 OLED 유기화합물 경쟁사 : 덕산네오룩\n",
    "memo_updated_at": "2026-01-09T00:34:48.159098+00:00"
  },
  {
    "corp_code": "00366438",
    "company_name": "산일전기(주)",
    "memo": "좋기좋못시 - 상\n\n사업 이해 O\n변압기 판매 산업\n\n해자\n특수 변압기(진입장벽 높음) 기술력 글로벌 상위권 (IR 보고서에서 글로벌 경쟁사와 비교했을 때 아직 탑 티어는 아니라고 명시되어있음.)\n글로벌 대기업 거래처와 장기간 거래중 (14년 이상)\n특수 변압기는 대체하기 어려운 기술\n\n주주친화성\n공식 홈페이지에 IR 공시 O\n상장한지(2024.7) 얼마 안 된 기업이라 유상증자 등 판단 기간 부족\n2024년 배당 이력 있음. 단일 년도 지표 (5.4%)\n상장 초기로 주주환원 정책은 아직 검증 단계.\n배당 이력은 있으나 정책화되었다고 보긴 이르다.\n\n산업 성향\n변압기 산업은 사이클이 있지만, 구조적 수요가 많은 편이다.\n\n매출 구조의 질\n2023, 2024, 2025 3Q 영업이익률 높다. -> 고부가구조 증명\n대형 고객사 장기간 거래중\n\n재무 안정성\n부채 낮음\n\n경영진\n오너 가족 지분율 55%로 좀 높은 편\n경영 안정성은 높으나, 주주환원, 지배구조 디스카운트 감안 필요. -> 추후 주주환원 이력 확인 필요\n\n특이사항\n2024년 상장을 위한 유상증자 금액으로 대규모 CAPEX 진행 -> 2024 FCF 음수인 이유.\n -> 추후 2025 3Q 매출 YOY 약 50% 상승 확인\n구리, 철강 등 원자재 원가에 영향 받습니다.\n\n개인적 감정 : 나의 심금을 울린 사업보고서의 내용 \n\"당사는 판매처와의 신뢰도를 중요하게 생각합니다. 자사 제품에 관련된 문의가 왔을 경우 최대한 신속하게 직원을 배치하여 판매처의 의견을 직접 듣고 해결책을 모색합니다.\" (기억으로 적었습니다)\n\n시장가 PER 41.1 PBR 8.0\n전기 평균 PER 15 ~ 20\n\n최종 판단\n굉장히 마음에 드는 기업이지만 시장가 프리미엄이 굉장히 붙은 상황.\nPER 20 ~ 25 정도 될 시 매수.\n추후 주주환원 정책 실행 확인 필요합니다. 해당 사항 없을 시 가격 디스카운트 감안해야합니다.",
    "memo_updated_at": "2026-01-22T02:24:26.835093+00:00"
  },
  {
    "corp_code": "01384787",
    "company_name": "(주)시프트업",
    "memo": "니케, 스텔라 블레이드를 만든 게임 개발 회사\n매수 안 함\n수입의 많은 부분을 금융 이자로 전환하고 있음, 연구 개발비는 3년 전보다 크게 줄어들었음. -> 현재 만든 게임만으로 만족하는 느낌이 들어 미래에 성장할 것이라는 생각이 들지 않음.",
    "memo_updated_at": "2026-01-12T03:07:03.559854+00:00"
  },
  {
    "corp_code": "01194689",
    "company_name": "에이치디현대마린솔루션(주)",
    "memo": "좋기좋못시 - 상\n사업 이해 O\n선박 및 엔진 after service, 벙커링(연료 공급)이 주 매출\n\n해자 무난\n벙커링 해자는 약한 편,\nAM 서비스는 락인 구조 해자 있는 편\n브랜드 있는 편\n\n주주친화성 좋은 편\n배당 수익률 2.5% (CFO에 따른 배당금이 아닌 고정적으로 배당금 증가, 그리고 배당 비율이 꽤 높다.)\n2024년 유상증자 이력 있음 : 기존 주주 가치 희석\n\n산업 성향\nCAPEX 필요성 낮은 편\n조선 사이클에 영향을 받지만, 주로 AM과 벙커링이 수익인만큼, 신규 조선보다는 운영중인 조선에 영향을 많이 받음.\n-> 호황에따른 실적 시차 존재할 수 있음\n-> 따라서 2023 - 2024 수주 많고, 2025 현재 상황에서는 수주 축소되었으니, 2027 - 2028쯤에는 매출액 감소 예상됨\n\n특이사항\n2025 3Q 매출액 YOY 대비 상승 확인 AND 신규 수주량 증가 확인\n\n시장가 PER 31.6 PBR 10.7\n\n총평\n좋기좋못시 - 상\n좋은 기업이다.\n자본 효율도 좋고, 각종 지표들도 우수.\n성장도 지속적으로 되고있고, 최근 2025 3Q에서도 지속 성장 확인함.\n다만 시장가가 너무 비싸서 관찰 대상으로 선정. 매수 포인트 달성 시 매수\n\n유지 사업상 수주 감소에 따른 운영 선박수 감소로 인한 2027 - 2028년도 매출액 감소 예상되는데, \n조선업 불황에 따른 PER 감소에 따라 매수했다가 매출액 감소로 인한 여파 맞을까 걱정됩니다.\n\n따라서 조선 수주가 늘어나고, 그 후 불황기가 왔을 때 가격이 가장 싼 기업이라고 생각되는데, 그게 지금임.\n하지만 지금 사기엔 너무 비싸 메리트 적다고 생각됨\n\n매수 포인트\nPER 20 이하 (현대 브랜드 메리트)",
    "memo_updated_at": "2026-01-26T01:27:26.479342+00:00"
  },
  {
    "corp_code": "01553129",
    "company_name": "주식회사 제이투케이바이오",
    "memo": "화장품 패스",
    "memo_updated_at": "2026-01-12T06:04:33.440161+00:00"
  },
  {
    "corp_code": "00262266",
    "company_name": "(주)삼현",
    "memo": "X\n모터, 제어기, 감속기 제품등을 모듈, 통합화 해서 판매하는 기업\n자동화, 무인화 방산, 로봇에 쓰인다.\n지표가 그렇게 좋아보이지 않는데 PER이 300인데요.. 미래 가치에 투자자들이 많이들 투자 한 것 같음. 나는 안한다",
    "memo_updated_at": "2026-01-12T06:21:56.070346+00:00"
  },
  {
    "corp_code": "01190568",
    "company_name": "(주)에이피알",
    "memo": "매수\n화장품 판매 산업 (주로 스킨 케어)\n판관비 높음, CAPEX 높음, 부채 높음 BUT 공격적 운영으로 시장 점유율 확보중. 상당히 공격적으로 운영하며 빠르게 커 나가고 있다. 그 부분이 마음에 들어서 최종 분석 후보에 추가",
    "memo_updated_at": "2026-01-12T06:42:33.796456+00:00"
  },
  {
    "corp_code": "01540815",
    "company_name": "주식회사 스튜디오삼익",
    "memo": "X\n홈퍼니싱 수요 조사, 유통업 산업\n주식은 발행했는데 CAPEX에 투자한 것도 아니고, 금융자산에 거의 대부분의 금액을 넣어버리는데, 성장 가능성이 아예 없다고 봅니다.",
    "memo_updated_at": "2026-01-12T07:02:34.525689+00:00"
  },
  {
    "corp_code": "01030503",
    "company_name": "(주)우진엔텍",
    "memo": "X\n원자력, 화력 발전소 정비 산업\nCFO 상승률이 너무 낮음",
    "memo_updated_at": "2026-01-12T07:06:34.524951+00:00"
  },
  {
    "corp_code": "00367710",
    "company_name": "(주)동인기연",
    "memo": "X\n골프 가방, 등산 가방, 캠핑용 용품 등을 만드는 회사\n사업 미래 가치 창출 한계가 있다고 생각됨.",
    "memo_updated_at": "2026-01-12T07:07:48.314397+00:00"
  },
  {
    "corp_code": "01226270",
    "company_name": "(주)스톰테크",
    "memo": "X\n정수기 관련 산업\n미래 가치 창출 한계 있다고 느낌",
    "memo_updated_at": "2026-01-12T07:08:31.470420+00:00"
  },
  {
    "corp_code": "01547933",
    "company_name": "(주)미쥬",
    "memo": "코넥스에 상장되어있어 거래 불가",
    "memo_updated_at": "2026-01-12T07:17:24.655681+00:00"
  },
  {
    "corp_code": "01027828",
    "company_name": "(주)퓨릿",
    "memo": "X\n반도체 케미컬 산업\nCFO 상승률 너무 낮음",
    "memo_updated_at": "2026-01-12T07:22:30.414410+00:00"
  },
  {
    "corp_code": "01467451",
    "company_name": "(주)케이티밀리의서재",
    "memo": "X\n주 매출은 월 구독료\n대한민국 전차잭 점유율 1등(60%), 꾸준한 영업 이익, CFO 상승률, 그리고 뉴스에 최근 활동 기록들이 굉장히 많은 게 인상적인 포인트였음\n하지만 매수는 다른 문제다 ..\n월 구독하러 간다잇",
    "memo_updated_at": "2026-01-14T06:02:22.514706+00:00"
  },
  {
    "corp_code": "00959210",
    "company_name": "코츠테크놀로지(주)",
    "memo": "X\n방산",
    "memo_updated_at": "2026-01-12T07:59:17.068143+00:00"
  },
  {
    "corp_code": "00158325",
    "company_name": "나이스평가정보 주식회사",
    "memo": "X\n신용 정보 관련 데이터 수집 && 판매 기업\n매출액 증가율이 낮음",
    "memo_updated_at": "2026-01-12T08:02:55.887073+00:00"
  },
  {
    "corp_code": "00447609",
    "company_name": "(주)비에이치",
    "memo": "X\nFPCB (RF쪽) 판매 산업 : FPCB에서 RF = 무선통신용 고주파 신호를 다루는 고급 FPCB\n수출, 내수 등 판매처는 대형 기업으로 좋지만,\n미래 가치 창출 지표가 낮다고 판단",
    "memo_updated_at": "2026-01-12T08:20:34.392531+00:00"
  },
  {
    "corp_code": "01136977",
    "company_name": "(주)마녀공장",
    "memo": "X\n화장품 산업 매출 대부분 클렌징\n성장률 미미",
    "memo_updated_at": "2026-01-12T20:55:16.765665+00:00"
  },
  {
    "corp_code": "01134216",
    "company_name": "주식회사 트루엔",
    "memo": "X\n카메라 기술 (IP) 산업\n지표들과 재투자, 성장하는 방면은 마음에 들지만 결국 성장 한계 있다고 생각\n",
    "memo_updated_at": "2026-01-12T21:04:54.940296+00:00"
  },
  {
    "corp_code": "01372782",
    "company_name": "(주)엑스게이트",
    "memo": "X\nVPN 산업\n성장 한계 있다고 생각",
    "memo_updated_at": "2026-01-12T21:06:38.061535+00:00"
  },
  {
    "corp_code": "00527002",
    "company_name": "(주)화인써키트",
    "memo": "X\nPCB(Printed Circuit Board)는 전자부품을 물리적으로 고정하고 전기적으로 연결하는 전자의 뼈대다.\n→ 회로 + 배선 + 기계적 지지 역할을 동시에 한다.\nCFO가 오락가락 너무 흔들림",
    "memo_updated_at": "2026-01-12T21:09:07.403948+00:00"
  },
  {
    "corp_code": "00925374",
    "company_name": "주식회사 윤성에프앤씨",
    "memo": "X\n2차전지 원재료 혼합 믹싱 장비 판매 기업\n매력에 비해 PER 너무 높음",
    "memo_updated_at": "2026-01-12T21:19:01.397755+00:00"
  },
  {
    "corp_code": "00525934",
    "company_name": "(주)엘엑스세미콘",
    "memo": "X\n당사는 팹리스 기업으로 Display Panel을 구동하는 핵심부품의 설계 및 제조, 판매를 주요 사업으로 영위하고 있는 시스템 반도체 기업입니다.\n성장 멈췄다고 판단",
    "memo_updated_at": "2026-01-12T21:22:49.572044+00:00"
  },
  {
    "corp_code": "01307335",
    "company_name": "주식회사 공구우먼",
    "memo": "X\n성장 멈췄다고 판단",
    "memo_updated_at": "2026-01-12T21:23:07.305397+00:00"
  },
  {
    "corp_code": "01357446",
    "company_name": "주식회사 퓨런티어",
    "memo": "X\n최근 기본 지표가 너무 안좋음",
    "memo_updated_at": "2026-01-12T21:23:34.914042+00:00"
  },
  {
    "corp_code": "01160974",
    "company_name": "주식회사 바이오에프디엔씨",
    "memo": "X",
    "memo_updated_at": "2026-01-12T21:23:49.897457+00:00"
  },
  {
    "corp_code": "01013694",
    "company_name": "인카금융서비스(주)",
    "memo": "X\n보험",
    "memo_updated_at": "2026-01-12T21:26:52.889664+00:00"
  },
  {
    "corp_code": "00922304",
    "company_name": "주식회사 아셈스",
    "memo": "X",
    "memo_updated_at": "2026-01-12T21:27:21.279051+00:00"
  },
  {
    "corp_code": "00604028",
    "company_name": "주식회사 피코그램",
    "memo": "X",
    "memo_updated_at": "2026-01-12T21:27:34.014232+00:00"
  },
  {
    "corp_code": "00958327",
    "company_name": "(주)지앤비에스 에코",
    "memo": "X\n당사는 2005년 설립 이후 지속적인 연구개발을 기반으로 글로벌 ESG 트렌드를 선도하고 있는 친환경 공정장비 전문 기업입니다. 반도체, 태양광, 디스플레이, 발전소 등다수의 핵심 산업 현장에서 발생하는 유해가스, 분진 등을 처리하는 공정장비를 개발 및 공급하고 있습니다. \n사업 성장 한계 있다고 판단",
    "memo_updated_at": "2026-01-12T21:29:02.530408+00:00"
  },
  {
    "corp_code": "00692254",
    "company_name": "(주)아이패밀리에스씨",
    "memo": "X\n2024년 CFO 음수일 때 주식을 발행함\n기존 주주 가치 훼손 우려",
    "memo_updated_at": "2026-01-12T21:33:42.537949+00:00"
  },
  {
    "corp_code": "01323032",
    "company_name": "케이카 주식회사",
    "memo": "X\n중고차 판매 산업\n영업이익률이 너무 낮아 구조상 한계가 있다고 판단",
    "memo_updated_at": "2026-01-12T21:38:51.976293+00:00"
  },
  {
    "corp_code": "00982023",
    "company_name": "주식회사 실리콘투",
    "memo": "매수\n화장품 유통\n판관비가 매우 적어 효율적인점\n메디큐브, 달바 등 유명한 브랜드가 해당 유통을 이용하는 점\n지표들이 우상향 하고있는 점\n단, 유통업 특성상 계약 락인이나 대체가 될 수 있다는 점에서 장기투자로써는 불안감이 있지만, 기업 자체에 관심이 생김\n\n주주친화적\n2024년 사업보고서에 향후 3년간 배당 계획 없다고 밝힘.\n자사주 소각 행보 X\n-> 완전 성장 집중\nIR 자료가 매우 풍부해 정보를 제공받기 좋다. 또한 각 나라에서 IR 개최를 굉장히 많이 하며 소통하는중.\n\n해자 \n해자가 약한 유통업 특성인데, 얘는 플랫폼 특성을 띔 (매출액, 영업이익률, 글로벌 상위권 화장품 기업들이 들어와있는 점, 공장에서 로봇을 이용한 시스템 개발 등)\n\n현금 사용처\n모두 산업 재투자 더 성장하려는 의지 보임 (2024년 사업보고서 기준)\n\n시장가 PER 19 PBR 7.7\n\n총평\nTOP 10 후보 결정\n이 정도 성장세를 보이는 회사는 관심이 간다.\n유통을 시스템과 플랫폼으로 만든 회사라고 판단함.\n현금사용처를 모두 재투자하고 배당에 신경쓰지 않는 등 성장 자체에 동력을 두고 있음은 나의 스타일\n보통놈이 아닌 느낌이 난다\n\n매매 위험신호\nTOP 1·2 매출 비중 ≥ 35%\n매출 증가 대비 판관비율 상승\n재고 회전율 감소",
    "memo_updated_at": "2026-01-26T11:02:47.032988+00:00"
  },
  {
    "corp_code": "00560849",
    "company_name": "(주)에스앤디",
    "memo": "X\n\n",
    "memo_updated_at": "2026-01-25T06:58:08.759073+00:00"
  },
  {
    "corp_code": "01390344",
    "company_name": "에이치디현대중공업(주)",
    "memo": "매수하지 않는다\n주 매출은 특수 조선 제작, 엔진 판매 7 : 3 정도\n산업 특성상 CAPEX 비용 자체가 높음. 이익률이 굉장히 낮은데, 부채 비율도 높아 대한민국 조선 사업이 경쟁력이 있지만 그로 인한 재무지표 건전성이 의심되어 투자 X",
    "memo_updated_at": "2026-01-12T04:21:37.922423+00:00"
  },
  {
    "corp_code": "00636656",
    "company_name": "바이오플러스 주식회사",
    "memo": "X\n미용",
    "memo_updated_at": "2026-01-12T23:01:35.752404+00:00"
  },
  {
    "corp_code": "01215618",
    "company_name": "(주)와이엠텍",
    "memo": "X\n매출액 CAGR 필터 오류",
    "memo_updated_at": "2026-01-12T23:05:42.068141+00:00"
  },
  {
    "corp_code": "00642897",
    "company_name": "브레인즈컴퍼니(주)",
    "memo": "X\n영업효율이 떨어지는게 보임",
    "memo_updated_at": "2026-01-12T23:10:48.481776+00:00"
  },
  {
    "corp_code": "00911229",
    "company_name": "(주)라온테크",
    "memo": "X\n영업이익률 너무 낮음",
    "memo_updated_at": "2026-01-12T23:12:40.815366+00:00"
  },
  {
    "corp_code": "01566248",
    "company_name": "주식회사 에코프로에이치엔",
    "memo": "X\n매출액 동결",
    "memo_updated_at": "2026-01-12T23:16:45.848061+00:00"
  },
  {
    "corp_code": "01568413",
    "company_name": "주식회사 에프앤에프",
    "memo": "O\n패션 (Discovery)\n판관비는 높은데, 원가가 낮아서 영업효율이 굉장히 좋다.\n현재 실적 동결로 매출액이 늘어나지 않고 있는데, 수입 구조가 회사가 성장할 것이라고 생각되어 매수 진행\n최근 FCF 음수 = CAPEX\n\n의심해야할 부분은 2022년부터 2025년까지 매출이 동결임. (분기보고서도 확인)\n매출이 동결인 이유, 어떻게 헤쳐나갈지에 대한 분석이 필요할 듯 일단 매수 후 추후 세부 분석 때 다룰 예정\n\n변화\n돈은 많이 버는데 보수적 운영 + 기업 성장이 이미 많이 되어 더 성장할 것 같지 않다는 생각",
    "memo_updated_at": "2026-01-26T00:19:32.065843+00:00"
  },
  {
    "corp_code": "01226410",
    "company_name": "(주)씨앤씨인터내셔널",
    "memo": "X\n화장품 ODM (제품을 기획하여 B2B 방식으로 기업에 파는 방식)\n영업이익률이 낮다고 생각되고, 사업구조상 한계가 있다고 판단\n",
    "memo_updated_at": "2026-01-13T00:19:29.839724+00:00"
  },
  {
    "corp_code": "01310773",
    "company_name": "(주)엔시스",
    "memo": "X\n2차전지\n가장 최근 2025 3Q 분기보고서에서 매출액이 감소함",
    "memo_updated_at": "2026-01-13T02:48:01.909510+00:00"
  },
  {
    "corp_code": "01532603",
    "company_name": "주식회사 화승알앤에이",
    "memo": "X\n영업이익률 너무 낮고 부채가 너무 많습니다",
    "memo_updated_at": "2026-01-13T02:51:02.714888+00:00"
  },
  {
    "corp_code": "01293953",
    "company_name": "주식회사 싸이버원",
    "memo": "X\n상장된지 오래됐는데 성장률이 너무 낮음",
    "memo_updated_at": "2026-01-13T02:53:10.439673+00:00"
  },
  {
    "corp_code": "01146822",
    "company_name": "(주)아이퀘스트",
    "memo": "X\n성장률 너무 낮음",
    "memo_updated_at": "2026-01-13T02:53:28.488041+00:00"
  },
  {
    "corp_code": "01159233",
    "company_name": "주식회사 솔루엠",
    "memo": "X\n전자기기 부품 연구개발 및 제조\n재투자가 계속 이루어지긴하지만, 실적이 좋아지지 않음. 투자하고 싶은 끌리는 이유를 딱히 찾지 못함",
    "memo_updated_at": "2026-01-13T02:57:08.963145+00:00"
  },
  {
    "corp_code": "00132202",
    "company_name": "선진뷰티사이언스(주)",
    "memo": "X\n화장품\n성장률에 비해 보고서에 써져있는 내용이 허세가 너무 가득함",
    "memo_updated_at": "2026-01-13T02:58:43.669969+00:00"
  },
  {
    "corp_code": "00921916",
    "company_name": "주식회사 석경에이티",
    "memo": "X\n너무 세부 사업임\n성장 한계 명확해보임",
    "memo_updated_at": "2026-01-13T02:59:47.313038+00:00"
  },
  {
    "corp_code": "00331016",
    "company_name": "(주)에프앤가이드",
    "memo": "X\n투자 가이드 홈페이지 운영\n수익 창출 구조가 명확하지 않다고 판단.",
    "memo_updated_at": "2026-01-13T03:02:19.987883+00:00"
  },
  {
    "corp_code": "00684802",
    "company_name": "주식회사 에이플러스에셋어드바이저",
    "memo": "X\n영업이익률 너무 낮음\n",
    "memo_updated_at": "2026-01-13T03:03:06.197966+00:00"
  },
  {
    "corp_code": "00608440",
    "company_name": "(주)티앤엘",
    "memo": "X\n상처 드레싱 \n지표는 좋은데 아들한테 주식 증여한다는 기사를 봄 -> 미래 불확실성",
    "memo_updated_at": "2026-01-13T03:08:11.381044+00:00"
  },
  {
    "corp_code": "01080252",
    "company_name": "주식회사 넥스틴",
    "memo": "반도체 전공정 PR 장비 판매 기업\n매출의 대부분을 중국에 의존\n영업이익률이 굉장히 높지만 시장 프리미엄이 이미 많이 붙음 (2026.01.08 기준 PER 60)\n같은 반도체 전공정 기술을 가진 산업 찾다가 PSK라는 기업에 더 메리트를 느낌 +\n프리미엄이 이미 너무 높게 잡힌거에 비해 안정성이 떨어진다고 생각하여 매수는 하지 않도록 결정",
    "memo_updated_at": null
  },
  {
    "corp_code": "01213586",
    "company_name": "아이디피(주)",
    "memo": "X\n데스크탑 카드프린터 판매 && 그에 따른 소비품도 판매\n성장률 부진",
    "memo_updated_at": "2026-01-13T03:15:04.841160+00:00"
  },
  {
    "corp_code": "01391103",
    "company_name": "(주)젝시믹스",
    "memo": "X\n성장세 미미",
    "memo_updated_at": "2026-01-13T03:21:08.348920+00:00"
  },
  {
    "corp_code": "00877174",
    "company_name": "(주)마크로밀엠브레인",
    "memo": "X\n성장세 미미",
    "memo_updated_at": "2026-01-13T03:21:24.215406+00:00"
  },
  {
    "corp_code": "00523936",
    "company_name": "에이치비솔루션(주)",
    "memo": "X\n지표 불안정",
    "memo_updated_at": "2026-01-13T03:22:07.281329+00:00"
  },
  {
    "corp_code": "01480568",
    "company_name": "(주)이지바이오",
    "memo": "사업 이해 O\n자돈사료 (25%) + 사료 첨가제 (75%)\n\n해자 약한편\n사료는 글로벌 분산시장\n자기업 IR 자료에서도 글로벌 사료 첨가\n\n주주친화성 좋은 편\n배당 수익률 3%\n자사주 소각 2025년 첫 공시\nIR 자료 풍부\n\n산업 성향\n완만한 성장\n구조적 성장 한계 있음\n사이클 낮음\n-> 구조적 성장 한계 있어 기업 성장에 따른 매수 / 매매 타이밍 고려해야함\n\n매출 구조의 질\n경쟁사가 많으나, 자돈 사업은 해당 기업의 프리미엄 제품임.\n해당 기업은 경쟁사중에서도 빠르게 성장하며 경쟁력 확보중.\n\n특이사항\n원재료 리스크 존재\n2025 3Q 매출액 YOY 대비 증가 확인\n\n시장가 PER 9.7 PBR 2.2\n\n총평\nTOP 10 후보 등록\n좋은 지표, 성장률, 좋은 시장가 등 좋은 지표들이 많다고 생각됨\n매수 / 매매 타이밍이 중요한 기업이라고 생각됩니다\n장기적으로 봤을 때 사업 구조상 성장 한계가 있다고 생각되어 기업이 어느정도 컸을 때\n매매 해야한다고 생각됨\n\n매매\n매출액 동결 등 기업 성장 한계가 왔다고 생각될 시\n\n2026 01 26\n산업 구조상 리스크 + 산업 구조상 낮은 ROIC를 벗어나기 어렵다는 한계\n-> TOP 10 후보 탈락",
    "memo_updated_at": "2026-01-26T11:07:50.497429+00:00"
  },
  {
    "corp_code": "00562245",
    "company_name": "주식회사 태웅로직스",
    "memo": "X\n유통\n매출액이 동결이거에 비해 영업이익률이 낮다",
    "memo_updated_at": "2026-01-13T09:27:28.438168+00:00"
  },
  {
    "corp_code": "01222432",
    "company_name": "주식회사 에스제이그룹",
    "memo": "X\n매출액 동결",
    "memo_updated_at": "2026-01-13T09:27:55.131052+00:00"
  },
  {
    "corp_code": "00367844",
    "company_name": "자이에스앤디(주)",
    "memo": "X\n건설\n건설업은 경쟁사도 많고 구조상 영업이익률이 너무 낮음 안 사",
    "memo_updated_at": "2026-01-13T09:33:33.849771+00:00"
  },
  {
    "corp_code": "00595182",
    "company_name": "주식회사 아톤",
    "memo": "X\n성장률 미미",
    "memo_updated_at": "2026-01-13T09:34:41.047679+00:00"
  },
  {
    "corp_code": "01069736",
    "company_name": "(주)한독크린텍",
    "memo": "X\n매출액 동결",
    "memo_updated_at": "2026-01-13T09:36:52.893103+00:00"
  },
  {
    "corp_code": "00876166",
    "company_name": "(주)케이비지",
    "memo": "X\nㅁㅊㅇ ㄷㄱ",
    "memo_updated_at": "2026-01-13T09:37:02.113079+00:00"
  },
  {
    "corp_code": "01365825",
    "company_name": "피에스케이 주식회사",
    "memo": "사업 이해 O\n\n해자\nDry Strip분야 글로벌 점유율 40%(2025 PSK IR 출처)\n전공정 필수단계이며, 국내, 해외 대기업에게 납품확인(2025 PSK IR 출처)\n\n주주친화성\n공시 IR은 없음.\n유상증자 X\n사이클 업황에서도 배당 정책 일관성 부족\n-> 타 반도체 기업에 비해서 주주친화성면에서 -요소 있다고 판단됨.\n\n현금 사용처\n최근 금융자산 축적중.\n3년간 일정한 CAPEX.\n\n산업 성향\n완전한 반도체 미세 공정 사이클 산업\n\n매출 구조의 질 O\n\n재무 안정성\n부채 비율 높지 않음.\n\n경영진\nPSK 홀딩스가 PSK 지분 32퍼 보유\n다른 자회사는 PSK 반도체 사업과 관련된 해외 지사들\n\n시장가 PER 15.3 PBR 2.2\n\n이 기업이 현재 수준의 수익성을 10년간 유지할 수 있는가?\n반도체 미세공정 사이클에 흔들릴 가능성 우려. 과거 반도체 불황때 방어 이력은 확인함.\n여러 우수한 지표들 확인.\n\n최종판단\n주주친화적 부분,  사업 구조상 다른 반도체 기업이 좀 더 메리트가 있다고 생각됨.\n관찰하며 해당 기업 저평가 됐을 때 매수 고려",
    "memo_updated_at": "2026-01-21T20:18:24.950442+00:00"
  },
  {
    "corp_code": "00611912",
    "company_name": "(주)아모그린텍",
    "memo": "X\nACD ER",
    "memo_updated_at": "2026-01-13T09:44:25.569589+00:00"
  },
  {
    "corp_code": "00323868",
    "company_name": "웹케시(주)",
    "memo": "X\n핀테크 산업\n산업 자체는 괜찮아보이고, 제휴 회사들 라인업도 괜찮은데,\n매출액 동결에 성장률이 낮은 상황에서 매수하기까지 매력은 느껴지지 않음",
    "memo_updated_at": "2026-01-13T09:56:40.512081+00:00"
  },
  {
    "corp_code": "01137903",
    "company_name": "(주)디케이티",
    "memo": "X\n영업이익률 너무 낮음",
    "memo_updated_at": "2026-01-13T09:58:14.748959+00:00"
  },
  {
    "corp_code": "01335578",
    "company_name": "(주)애니플러스",
    "memo": "X\n애니 산업은 성장 한계 있다고 생각",
    "memo_updated_at": "2026-01-13T10:04:13.624697+00:00"
  },
  {
    "corp_code": "00531829",
    "company_name": "(주)엠아이텍",
    "memo": "X\n비혈관용 스탠드 판매\n아이템 좋고, 영업 이익률 좋고, 효율 좋지만 결국 매출액이 커지지 않음. 성장 가능성이 낮다고 판단됨",
    "memo_updated_at": "2026-01-13T10:08:27.421614+00:00"
  },
  {
    "corp_code": "00811372",
    "company_name": "(주)노바렉스",
    "memo": "X\nACD ER",
    "memo_updated_at": "2026-01-13T10:08:40.527355+00:00"
  },
  {
    "corp_code": "01181515",
    "company_name": "(주)엘앤씨바이오",
    "memo": "X\n성형관련\n영업이익률이 갈 수록 적어짐 -> 효율성이 떨어진다고 판단됨 && 매출액 성장률은 높지만 시장 자체가 작다고 판단",
    "memo_updated_at": "2026-01-13T10:10:49.494210+00:00"
  },
  {
    "corp_code": "01325979",
    "company_name": "(주)세아제강",
    "memo": "O\n강관산업 \n국내 기준 시총, 매출, 영업이익률 1등\n기본적으로 자리가 잡혀있는 산업인데, 각종 지표들 훌륭함.\n최근 분기보고서 (2025 3Q) 성적은 좋지 않다. 하지만 내재 가치가 뛰어나다고 생각합니다.\n최근 성적이 좋지 않자 자사주 매입해서 소각함 -> 자신도 있고, 주주 친화적이라고 생각이 드는 행보\n내재가치에 비해 시장가격이 좀 저평가 되어있다고 생각이 됩니다. (PER 3배)\n\n-> 변경 \n지표 좋고 점유율 좋은 회사지만, 장기투자로써는 적합하지 않다고 판단.\n\n\n\n",
    "memo_updated_at": "2026-01-25T22:47:56.461415+00:00"
  },
  {
    "corp_code": "00867849",
    "company_name": "(주)오파스넷",
    "memo": "X\n네트워크 산업\n투하 자본에 비해 버는 효율이 좋지만 궁극적으로 영업이익률이 너무 낮다.(5퍼 부근)",
    "memo_updated_at": "2026-01-13T10:36:09.568388+00:00"
  },
  {
    "corp_code": "01251577",
    "company_name": "주식회사 휴네시온",
    "memo": "X\n성장률 낮음",
    "memo_updated_at": "2026-01-13T10:36:47.195965+00:00"
  },
  {
    "corp_code": "01309795",
    "company_name": "(주)알로이스",
    "memo": "X\n매출 성장률 낮음 ",
    "memo_updated_at": "2026-01-13T10:37:05.361143+00:00"
  },
  {
    "corp_code": "01316254",
    "company_name": "에이치에스효성첨단소재(주)",
    "memo": "X\n산업자재 부문에는 타이어보강재, 산업용 원사, 카페트, 아라미드, 탄소섬유 등이 있습니다.\n영업이익률 낮은데, 해당 분야에서 점유율이 1~2등권이 아니다",
    "memo_updated_at": "2026-01-13T10:40:23.260373+00:00"
  },
  {
    "corp_code": "01316227",
    "company_name": "효성티앤씨(주)",
    "memo": "X\n섬유\n영업이익률 너무 낮음",
    "memo_updated_at": "2026-01-13T10:42:09.911038+00:00"
  },
  {
    "corp_code": "00799539",
    "company_name": "(주)제노레이",
    "memo": "X\nX-RAY 관련 장비\n성장률 미미, 영업이익률 너무 낮음",
    "memo_updated_at": "2026-01-13T10:44:46.551481+00:00"
  },
  {
    "corp_code": "01170865",
    "company_name": "(주)네오셈",
    "memo": "X\n반도체 후공정\n최근 반도체 사이클 왔을 때 매출이 떨어짐.",
    "memo_updated_at": "2026-01-13T21:27:14.684283+00:00"
  },
  {
    "corp_code": "00413046",
    "company_name": "(주)셀트리온",
    "memo": "X\n바이오같지만 대량 생산, 유통 기업이라고 판단함 그에 비해 PER이 너무 높다\n합병 후 지표 회복이 너무 느림",
    "memo_updated_at": "2026-01-13T21:53:55.068570+00:00"
  },
  {
    "corp_code": "00605328",
    "company_name": "씨앤지하이테크(주)",
    "memo": "X\n반도체\n총자산영업이익률, ROE 부분에서 메리트 못 느낌",
    "memo_updated_at": "2026-01-13T21:58:00.780841+00:00"
  },
  {
    "corp_code": "01267684",
    "company_name": "쿠쿠홈시스 주식회사",
    "memo": "X\n정수기, 비데, 공청기, 안마의자 등 판매 && 렌탈 사업\n성장 한계 있다고 판단 해당하는 제품들은 생필품이 아님 ",
    "memo_updated_at": "2026-01-13T22:01:39.184801+00:00"
  },
  {
    "corp_code": "01255652",
    "company_name": "(주)레이크머티리얼즈",
    "memo": "X\n매출액이 느는데 영업이익은 줄어든다. ",
    "memo_updated_at": "2026-01-13T22:06:46.063069+00:00"
  },
  {
    "corp_code": "01263022",
    "company_name": "(주)비지에프리테일",
    "memo": "X\nCU\n구조상 영업이익률이 너무 낮다\n경쟁사도 많은데",
    "memo_updated_at": "2026-01-13T22:08:38.314949+00:00"
  },
  {
    "corp_code": "01261893",
    "company_name": "(주)케이씨텍",
    "memo": "X",
    "memo_updated_at": "2026-01-13T22:09:05.754508+00:00"
  },
  {
    "corp_code": "00962223",
    "company_name": "지니언스(주)",
    "memo": "X",
    "memo_updated_at": "2026-01-25T22:31:08.141834+00:00"
  },
  {
    "corp_code": "01186404",
    "company_name": "주식회사 디앤씨미디어",
    "memo": "X\n웹툰, 웹소설",
    "memo_updated_at": "2026-01-13T22:36:31.470089+00:00"
  },
  {
    "corp_code": "01237540",
    "company_name": "(주)이녹스첨단소재",
    "memo": "사업 이해\nOLED (57%)\n회로 소재(34%)\n반도체용 PKG소재(9%)\n2026년부터 수산화리튬 생산 가동, IR에서 2030년 수산화리튬 총 매출의 50% 목표로 세움.\n\n해자\nOLED 소재\n글로벌 주요 OLED 패널사 대부분에 공급\n고객별 승인·공동개발 구조 → 전환비용 존재\n\n회로 소재\n국내 시장 과점\n브랜드·인지도·원가경쟁력 보유\n\n반도체 PKG 소재\n국내 유일 Full line-up\n삼성전자, SK하이닉스 승인 구조\n\n대체 가능성\n이론적 가능\n실무적 대체 어려움 (수율·신뢰성)\n\n→ 기술 기반 전환비용형 해자\n→ 독점은 아님\n\n주주친화성 O\n\n산업 성향\n명확한 사이클 산업\n\n재무 안정성\n채무 과도하지 않음\n\n주주 환원 && 경영진\n주식 소각을 매 년 50% 늘리겠다고 약속, 2024년 기준 해당 약속을 이행한 상태임.\n+ 2025년도에도 주식 소각 진행 확인\n\n특이사항\n수산화리튬 생산을 위한 대규모 CAPEX를 계속 진행해왔고, 2026년 상반기부터 생산 예정.\n2026년 상반기부터 수산화리튬 연산 2만톤 공장으로 생산 후 국내 글로벌 대형사에게 공급 예정 (계약 완료)\n-> 추후 공장 가동률, 실적 등 확인 필요\n\n시장가 PER 7.0 PBR 1.2\n\n최종 판단\n장기 투자로써는 불안.\n단기 사이클 투자로 적합\n최근 수산화리튬 생산을 위해 전력을 다하는 중인데,\n실적 확인하기 전 상황인데 베팅할만한다고 생각 (수주를 이미 계약했기 떄문에 저점 있다고 판단 + 수산화리튬 생산을 위한 투자가 현재 사업에 수익률로 전환되지 않은 상황에 저평가여지, 상승 여력 있다고 생각됨.)\n\n-> 베팅할 만 하다고 생각됨",
    "memo_updated_at": "2026-01-23T00:25:13.172205+00:00"
  },
  {
    "corp_code": "01238169",
    "company_name": "(주)오리온",
    "memo": "O\n부채 없고, 지표 좋고, 영업이익률 좋고.\n걱정되는건 성장한계가 있을 것 같긴한데..\n삼양과 같이 나중에 식품 세부 분석\n\n사업 이해 O\n제과 단일 사업\n\n해자 양호한 편\n경쟁사 많음\n중국 파이류 최상위 브랜드\n해당 기업의 기본적인 브랜드가 존재함\n\n주주친화성 무난한 편\nIR 자료 풍부\n유상증자 X\n배당수익률 2.15%\n\n산업 성향\n필수소비재\n구조적 완만 성향\n\n매출 구조의 질\n가격 결정권 브랜드력으로 인한 특정 제품에 대해서는 높음 (파이류)\n\n특이사항\n이미 성장을 이룬 기업이라 폭발적 성향 제한\n밸류업공시 보고서에 공장 증축 등 8300억 + a 투자 계획 있음\n\n시장가\nPER 8.7 PBR 1.3\n\n총평\nTOP 10 후보 등록\n장기적 완만한 성장이 기대되는 기업\n각종 지표 좋고 부채 없고 모난점이 없는 기업\n걱정되는건 성장 한계 있다고 판단됨.\n\n매매\n매출액 2년 이상 동결 시(성장 동결 시)\n\n2026 01 26 +\nTOP 10 후보 탈락\n꾸준한 성장 예상되지만, 이미 어느정도 성장 + 다른 성장률 높은 기업 매물이 더 매력적이라고 판단",
    "memo_updated_at": "2026-01-26T08:55:14.276461+00:00"
  },
  {
    "corp_code": "01124680",
    "company_name": "(주)보라티알",
    "memo": "X\n파스타 관련 식품 수입, 유통\n가공식품수입, 유통 모두 맘에 안들어",
    "memo_updated_at": "2026-01-13T23:52:20.523625+00:00"
  },
  {
    "corp_code": "01199189",
    "company_name": "(주)이랜시스",
    "memo": "X\n생활가전제품 (로봇청소기, 공기ㆍ의류 청정기, 정수기외) 및 보안 솔루션 제품(디지털 도어록 및 각     종 잠금장치)의 핵심부품를 자체 설계\n성장률 미미",
    "memo_updated_at": "2026-01-13T23:55:23.443312+00:00"
  },
  {
    "corp_code": "01234297",
    "company_name": "미원스페셜티케미칼(주)",
    "memo": "X\n에너지경화수지(UV/EB curable resin)를 생산\n성장 한계 있다고 생각",
    "memo_updated_at": "2026-01-13T23:57:30.019110+00:00"
  },
  {
    "corp_code": "01205851",
    "company_name": "에이치디현대일렉트릭(주)",
    "memo": "좋기좋못시 - 중\n사업 이해\n전력공급 과정 전 단계 중 송.변전 중심 전기전자기기 제조\n\n해자\n전환비용 O\n국제 인증 O\n사우디, 아메리칸일렉트릭파워, 한국전력공사등 유틸리티 레퍼런스 보유\n독점은 아님. 입찰 가능한 업체 수가 제한되는 구조.\n\n주주친화성\n2024년부터 배당금이 늘었는데, 연결 기준 실질 배당성향 약 15.2%\n자사주 소각/추가 매입 계획 없다고 명시\n\n현금 사용처\n많은 이익이 발생한 년도가 한정적이라 2024년 단일 기준으로 서술\n2024년 CFO의 약 70%는 부채 상환에 쓰였음. 또한 규모 있는 CAPEX, 배당 시행\n\n산업 성향\nAI·데이터센터·신재생·유틸리티 CAPEX가 호황일수록 좋고,\n사이클은 있지만 망하지 않는 인프라 사이클 산업이다.\n\n매출 구조의 질\n좋은 판매처를 가지고 있으나(해자에 기재),\n경기 하강 + 사이클시 가격 인하 압력 큼\n\n재무 안정성\n자본집약 산업 특성상 순차입 구조는 불가피하나,\n최근 실적 개선으로 단기 상황 여력이 확보됨.\n\n경영진\n모 회사 현대 지분율 35%\n그룹 계열 매출이 의심되었으나, 외부 시장에서 경쟁력 있는 독립 수주 기업임.\n\n특수사항\n2024년 생산능력 증가를 위한 CAPEX 이후 2025 3Q 매출액 YOY 증가 확인\n추후 매출액 증가 여부도 확인 필요\nCAPEX 집행 이후 생산능력 가동 시점에 따른 매출 실적 반영 시차 존재할 수 있음\n\n시장가 PER 52.5 PBR 18.2\n\n최종 판단\n추가 확인해야 할 내용 있고 현재 가격은 프리미엄이 많이 붙었다.\n최근 관련 섹터 호황에 따른 프리미엄이 많이 붙었다고 생각\n섹터 호황이 줄어들었을 때 이익이 유지되는지 확인 필요. \n해당 부분 확인 시 좋은 기업은 맞다.\n해당 산업 평균 PER은 15 ~ 20.\n\n1. 기업 펀더멘털 유지,\n2. PER 25 이하이며,\n3. 국가 수주 / 지표들이 건전할 시\n매수 고려\n\n1. 수주잔고 YoY 감소\n2. 가동률 85% 이하\n3. 해당 기업 펀더멘털 자체 가치 하락시\n매매",
    "memo_updated_at": "2026-01-22T03:54:23.239875+00:00"
  },
  {
    "corp_code": "00660750",
    "company_name": "하나머티리얼즈(주)",
    "memo": "X\n반도체 사이클인데 매출 증가 없음(2025 분기보고서 기준)",
    "memo_updated_at": "2026-01-14T00:19:24.099103+00:00"
  },
  {
    "corp_code": "01205329",
    "company_name": "(주)크라운제과",
    "memo": "X\n과자쪽은 지표가 더 좋은 경쟁자가 있음 (오리온, 삼양)",
    "memo_updated_at": "2026-01-14T00:19:51.534686+00:00"
  },
  {
    "corp_code": "00997812",
    "company_name": "(주)코미코",
    "memo": "X\n반도체 공정\n부채가 너무 많은데 어디에 쓰는지 모르겠음",
    "memo_updated_at": "2026-01-14T00:27:04.307847+00:00"
  },
  {
    "corp_code": "00526599",
    "company_name": "(주)덴티움",
    "memo": "X\n임플란트\n부채로 CAPEX 증가. 하지만 실적 좋지 않음",
    "memo_updated_at": "2026-01-14T00:32:06.322392+00:00"
  },
  {
    "corp_code": "01113754",
    "company_name": "티이엠씨씨엔에스(주)",
    "memo": "X",
    "memo_updated_at": "2026-01-14T00:33:20.651083+00:00"
  },
  {
    "corp_code": "00877059",
    "company_name": "삼성바이오로직스(주)",
    "memo": "좋기좋못시 - 상\n사업 이해 O\nCDMO, CMO\n\n해자 강함\n대규모 CAPEX 세계에서도 이렇게 공장 투자할 수 있는 기업 없음\n\n주주친화성 낮음\n2022년 CAPEX 목적 유상증자 1회\n배당, 자사주 소각 등은 없음 -> 성장 위주\n\n산업 성향 좋음\n구조적 성장 강함\n사이클 X\n\n특이사항\n대규모 CAPEX를 통한 CMO 산업 점유율을 높이려는 목적으로 보임 -> ROIC 낮은 이유\n2025 3Q 공장 가동률 70퍼센트 확인\n2025 3Q 매출액 증가 확인\n\n시장가 PER 80.4 PBR 10.5\n\n총평\n좋기좋못시 - 상\n기업 가치 높음\n뛰어난 영업이익률, 바이오사업에 따른 미래 기대치, 공격적인 CAPEX를 통한 글로벌 CMO 사업 점유율 증가 기대 등\n강한 해자, 최근 지표도 상승세\n하지만 가격이 너무 높다. 지금이 제일 저렴할 수 있지만, CAPEX 증설 결과 확인 후 조정 때 들어가도 늦지 않다고 생각됨\n결국 꾸준히 성장할것으로 예상됨 따라서 가격 조정 시 매수한다.\n\n매수 신호\n1. CAPEX 증설 계획은 아래와 같습니다. 추후 계획 변경 있을 수 있습니다.\nPlant 5: 2025년 4월 완료 (180 kL)\nPlant 6: 2032년 예정 (180 kL)\nPlant 7: 2032년 예정 (180 kL)\nPlant 8: 2032년 예정 (180 kL)\n각 Plnat에 따라 실적 증가 확인, 가동률(최소 70% 이상) 필요합니다. (2025 3Q 공장 가동률 70퍼센트 확인)\n\n2. 1번이 충족될 시, PER 40 이하일 시 매수(삼성 브랜드 +)",
    "memo_updated_at": "2026-01-26T02:18:49.175642+00:00"
  },
  {
    "corp_code": "01073678",
    "company_name": "(주)얼라인드제네틱스",
    "memo": "X\n성장률 미미",
    "memo_updated_at": "2026-01-14T00:54:13.809516+00:00"
  },
  {
    "corp_code": "00819073",
    "company_name": "인크로스(주)",
    "memo": "X\n광고\n매출액, 영업이익, ROIC 지속적 감소 ",
    "memo_updated_at": "2026-01-14T01:46:30.646825+00:00"
  },
  {
    "corp_code": "00225706",
    "company_name": "제이더블유생명과학(주)",
    "memo": "X\n연결 기업과 거래 매출이 75퍼센트\n",
    "memo_updated_at": "2026-01-14T01:52:11.575329+00:00"
  },
  {
    "corp_code": "00527464",
    "company_name": "(주)에이치시티",
    "memo": "x",
    "memo_updated_at": "2026-01-14T01:52:34.452451+00:00"
  },
  {
    "corp_code": "01165739",
    "company_name": "잉글우드랩 주식회사",
    "memo": "X\n화장품",
    "memo_updated_at": "2026-01-14T01:56:46.068198+00:00"
  },
  {
    "corp_code": "01029394",
    "company_name": "(주)에코마케팅",
    "memo": "x\n마케팅, 의류 제조 및 판매\n기업운영방식이 보고서에 자세히 적혀 있고, 해당하는 부분의 설명이 굉장히 마음에 들지만,\n최근 매출액동결, 자본효율 악화. -> 추후 이유 설명\n개인적으로는 CEO에 매력이 있어보이는데 최근 베인캐피탈(사모펀드)가 해당 회사 인수하려고 대표에게 40% 가량의 주식을 매입.\n",
    "memo_updated_at": "2026-01-14T02:12:47.089298+00:00"
  },
  {
    "corp_code": "01032413",
    "company_name": "해성디에스(주)",
    "memo": "X\n반도체\n최근 반도체 사이클에 매출 늘지 않음",
    "memo_updated_at": "2026-01-14T02:13:52.129886+00:00"
  },
  {
    "corp_code": "01159853",
    "company_name": "(주)휴온스",
    "memo": "ㅌ\n영업이익률이 너무 낮다",
    "memo_updated_at": "2026-01-14T02:14:38.392156+00:00"
  },
  {
    "corp_code": "01124653",
    "company_name": "(주)슈프리마",
    "memo": "ㅌ\n성장한계있다고생각",
    "memo_updated_at": "2026-01-14T02:15:40.433956+00:00"
  },
  {
    "corp_code": "00332927",
    "company_name": "(주)제이에스코퍼레이션",
    "memo": "X\n핸드백산업",
    "memo_updated_at": "2026-01-14T02:16:37.356806+00:00"
  },
  {
    "corp_code": "00879020",
    "company_name": "(주)유니트론텍",
    "memo": "X\n유통",
    "memo_updated_at": "2026-01-14T02:25:28.519073+00:00"
  },
  {
    "corp_code": "00568461",
    "company_name": "(주)에이치씨보광산업",
    "memo": "ㅌ",
    "memo_updated_at": "2026-01-14T02:25:53.003015+00:00"
  },
  {
    "corp_code": "00244747",
    "company_name": "(주)파크시스템스",
    "memo": "사업 이해 O (AFM : 원자현미경)\n니치 산업\n\n사업 해자 최상\n글로벌 산업 AFM 점유율 압도적 1등\n연구용 AFM은 점유율이 20%정도 경쟁사가 있다\n해당 기업의 산업 AFM 기술력은 경쟁사가 따라할 수 없다고 자체 보고서에 명시\n\n주주환원 X\n배당성향 작음. 성장주\n자사주 소각 X\n유상증자 이력은 없음.\n\n매출의 질 우수\nAFM 판매(약 70%)와 그 소비품(약 30%)\n글로벌 대기업들에게 판매함\n\n경영진 우수\nCEO\n창업자 + 30년 이상 AFM 한 분야\n말과 행동 일치 (AFM 집중 전략 유지)\n\n산업 성향\n완전한 사이클 산업 아님\n반도체 CAPEX 영향 받지만,\n사이클 + 구조적 성장 혼합\n\n시장가 PER 34.6 PBR 7.7\n\n총평\n장투로 가지고 갈 만한 기업이다. 근데 너무 비싼데 산업 자체가 무너지지 않는 한 가격이 크게 떨어질 일 없어보임\n소량만 일단 들고간다 TOP 10 후보에도 넣겠음\n\n매매\n산업적 AFM 수요 감소\nAFM 교체 주기는 긴 편. 신 기술이 나오지 않는 이상 매출액 동결 시(기존 AFM 대량 판매하여 판매처가 부족하다고 판단 시)\n\n2026 01 26\nTOP 10 후보 제외\n엄청나게 좋은 기업인건 확실.\n하지만 성장률에 비해 너무 높은 PER이 아닌가?\n성장하려면 시간이 좀 걸릴 듯 한데 선반영 너무 많이 되어있다고 생각",
    "memo_updated_at": "2026-01-26T09:23:42.183688+00:00"
  },
  {
    "corp_code": "00549891",
    "company_name": "(주)케어젠",
    "memo": "X\n내가 생각한 내재가치보다 시장 평가가 너무 높음\n",
    "memo_updated_at": "2026-01-14T06:30:01.614990+00:00"
  },
  {
    "corp_code": "01066058",
    "company_name": "(주)파마리서치바이오",
    "memo": "코스닥 상장 X",
    "memo_updated_at": "2026-01-14T06:31:19.014239+00:00"
  },
  {
    "corp_code": "01108099",
    "company_name": "현대코퍼레이션홀딩스(주)",
    "memo": "x\n정보 부족",
    "memo_updated_at": "2026-01-14T06:37:47.029747+00:00"
  },
  {
    "corp_code": "01101041",
    "company_name": "패션플랫폼(주)",
    "memo": "ㅌ\n성장률미미",
    "memo_updated_at": "2026-01-14T06:38:00.902551+00:00"
  },
  {
    "corp_code": "00503668",
    "company_name": "엘아이지넥스원(주)",
    "memo": "X\n방산",
    "memo_updated_at": "2026-01-14T06:42:10.729235+00:00"
  },
  {
    "corp_code": "00666204",
    "company_name": "제너셈(주)",
    "memo": "ㅌ",
    "memo_updated_at": "2026-01-14T06:43:22.685439+00:00"
  },
  {
    "corp_code": "00970453",
    "company_name": "(주)파마리서치",
    "memo": "X\n피부 미용\n솔직히 영업 이익률, 성장세 봤을 때 좋은 매물 같은데,\n사업 자체에 관심이 좀 없어서 패스",
    "memo_updated_at": "2026-01-14T06:50:36.012672+00:00"
  },
  {
    "corp_code": "00565154",
    "company_name": "(주)이노션",
    "memo": "X\n광고대행\n영업이익률이 넘 낮다",
    "memo_updated_at": "2026-01-14T06:53:14.073560+00:00"
  },
  {
    "corp_code": "01013311",
    "company_name": "(주)헥토이노베이션",
    "memo": "X\n보안\n지표가 무난하게 좋지만.. 끌리지 않는다",
    "memo_updated_at": "2026-01-14T06:55:20.270049+00:00"
  },
  {
    "corp_code": "00508344",
    "company_name": "SK디앤디(주)",
    "memo": "X\n부동산..?\n산업 구조 이해 X",
    "memo_updated_at": "2026-01-14T06:59:18.139448+00:00"
  },
  {
    "corp_code": "01074862",
    "company_name": "메가스터디교육(주)",
    "memo": "X\n해당 산업 관심 없음",
    "memo_updated_at": "2026-01-14T07:00:34.760676+00:00"
  },
  {
    "corp_code": "01067516",
    "company_name": "(주)골프존",
    "memo": "ㅌ\n성장 한계 있다고 생각",
    "memo_updated_at": "2026-01-14T07:01:48.369359+00:00"
  },
  {
    "corp_code": "01061327",
    "company_name": "(주)클래시스",
    "memo": "사업 이해 O\n해당 기업은 피부미용 의료기기, 미용 소모품 판매를 50 : 50으로 영위하고 있습니다.\n클래시스는 병원 시술용 EBD 장비를 설치(Platform)로 깔고, 그 설치 기반에서 소모품을 반복 판매해 이익을 쌓는 구조이며, \n해외 확장·제품 업그레이드·포트폴리오 확장이 성장 레버다.\n-> 장비를 팔면 소모품에 대한 지속적 수요가 발생하는 구조가 굉장히 마음에 듭니다.\n\n해자\nHIFU 글로벌 강자, 누적 설치 18,000대+\nRF는 후발주자이지만 FDA 조기 승인으로 미국 진입\n경쟁은 치열, 기술 자체도 대체 가능\n차별 요소 :\n임상 논문 다수\n글로벌 KOL 네트워크 200+\nand 장비 락인 구조\n\n주주친화성\n유상증자 X\n배당성향은 연결순이익 기준 10% 정도.\nIR, 공시 자료 풍부함. 타 기업과 비교했을 때 IR 분량, 빈도가 굉장히 우수한 편(국내, 해외 모두 실시중).\n\n현금 사용처\n2021년 350억가량 장기차입금 -> CAPEX에 그대로 재투자 이력 있음.\n지속적인 CAPEX 보다는 일정 기간(약 3년쯤?)마다 CAPEX 투자 내역 있음.\n최근 2024년 사업보고서에는 늘어난 수입을 저축중.\n\n산업 현황\n피부 미용인 만큼 경기에 영향을 많이 받을 것.\n\n매출 구조의 질\n경쟁사가 많으나, 브랜드 / 락인 구조로 협상력을 보유한다.\n반복성 매출인 소모품의 비율이 약 50%라 판매처만 늘릴 수 있다면 매출 구조의 질은 우수한 편.\n-> 가장 최근(2025 3Q) 매출액 YOY 약 30% 증가 확인\n\n재무 안정성\n부채 비율 낮음\n\n경영진\n공식 IR에 각 부서 헤드들의 경력 적혀있음.\n글로벌 탑티어 출신들이 다수.\n\n말–행동 일치:\nFDA 조기 승인 (IR에 초기 계획보다 8개월 앞당겨 승인이라고 명시)\n글로벌 확장 실제 진행 (매출 해외 비율 상승)\n\n특이사항\n\n시장가 PER 33.1 PBR 7.5\n\n최종 판단\n이놈은 큰다\nPER 33배여도 구매할 만 하다고 생각된다 \n매수 TOP 10 후보에 추가\n\n매매\n성장 둔화 신호",
    "memo_updated_at": "2026-01-26T11:11:23.836217+00:00"
  },
  {
    "corp_code": "01061558",
    "company_name": "덕산네오룩스(주)",
    "memo": "좋기좋못시 - 하\nOLED 하청 기업,\n좋은 기술력으로 삼성디스플레이에 납품중\n기술 변환 해자 있음\n사업 결정권 X, 가격 결정권 낮음, \n사이클 + 구조적 성장 산업 반반, \nIR 자료 많지만 자사주 소각 X, 배당 X 등 주주친화적인 행보는 없음.\n\n=> 장투 X \n매수 포인트\n삼성디스플레이 IT용 OLED CAPEX 집행 징후 포착 시 \nPER 10 이하 등 가격이 굉장히 저렴해졌을 시",
    "memo_updated_at": "2026-01-23T01:53:12.467666+00:00"
  },
  {
    "corp_code": "01059605",
    "company_name": "디와이파워(주)",
    "memo": "X\n성장동결",
    "memo_updated_at": "2026-01-14T07:15:29.170342+00:00"
  },
  {
    "corp_code": "00614478",
    "company_name": "(주)휴메딕스",
    "memo": "X\n미용",
    "memo_updated_at": "2026-01-14T07:19:41.309975+00:00"
  },
  {
    "corp_code": "01047415",
    "company_name": "(주)정다운",
    "memo": "ㅌ\n성장동결",
    "memo_updated_at": "2026-01-14T07:19:52.753940+00:00"
  },
  {
    "corp_code": "00126186",
    "company_name": "삼성에스디에스(주)",
    "memo": "사업 구조는 아마존과 비슷한 느낌\n매출 비율 (대략)\n물류 : 50\nIT 아웃소싱 : 20\n클라우드 : 15\nSI : 7\n\n클라우드를 직접 만들고 서비스하는 산업 + 국제적 물류센터를 운영\n\n매출 성장 정체 + 사업 집중도가 떨어진다고 판단됨.\n매수하지 않는다\n",
    "memo_updated_at": null
  },
  {
    "corp_code": "00917861",
    "company_name": "(주)슈피겐코리아",
    "memo": "성장동결",
    "memo_updated_at": "2026-01-14T07:20:19.011334+00:00"
  },
  {
    "corp_code": "01038693",
    "company_name": "(주)드림시큐리티",
    "memo": "ㅌ\n보안\n성장세미미",
    "memo_updated_at": "2026-01-14T07:21:19.588937+00:00"
  },
  {
    "corp_code": "00132354",
    "company_name": "쿠쿠홀딩스(주)",
    "memo": "ㅌ\n이익률하락",
    "memo_updated_at": "2026-01-14T07:22:27.890223+00:00"
  },
  {
    "corp_code": "01032404",
    "company_name": "콜마비앤에이치(주)",
    "memo": "ㅌ",
    "memo_updated_at": "2026-01-14T07:23:04.526786+00:00"
  },
  {
    "corp_code": "00656951",
    "company_name": "(주)현대이지웰",
    "memo": "ㅌ\n직원 복지 사업\n필수가 아니다 성과금이 복지지 다른것이 복지겠는가",
    "memo_updated_at": "2026-01-14T07:24:17.668943+00:00"
  },
  {
    "corp_code": "00992871",
    "company_name": "(주)종근당",
    "memo": "X\n해외진출 없이는 더 성장할 수 없다고 판단",
    "memo_updated_at": "2026-01-14T07:26:44.004824+00:00"
  },
  {
    "corp_code": "00563545",
    "company_name": "(주)두산테스나",
    "memo": "ㅌ\n뭔가 이상하다 .. 거래량이 왜 이렇게 많은지도 모르겠고 주가가 왜 이렇게 왔다갔다하는지도 잘 모르겠음\n지표 자체도 그렇게 매력적이지않아서 패스",
    "memo_updated_at": "2026-01-14T07:31:22.323717+00:00"
  },
  {
    "corp_code": "00638487",
    "company_name": "(주)파수",
    "memo": "ㅌ",
    "memo_updated_at": "2026-01-14T07:31:31.607528+00:00"
  },
  {
    "corp_code": "00626464",
    "company_name": "(주)지엔씨에너지",
    "memo": "ㅌ\n지표 우상향에 보고서 보면 좋아보이는데 뭔가 확신이 들지 않음",
    "memo_updated_at": "2026-01-14T07:48:07.051526+00:00"
  },
  {
    "corp_code": "00492353",
    "company_name": "(주)파이오링크",
    "memo": "X\n성장동결\n",
    "memo_updated_at": "2026-01-14T07:48:41.538045+00:00"
  },
  {
    "corp_code": "00366137",
    "company_name": "케이지에코솔루션(주)",
    "memo": "X\n합병 후 자리 못 찾는 느낌",
    "memo_updated_at": "2026-01-14T07:51:08.323375+00:00"
  },
  {
    "corp_code": "00625942",
    "company_name": "한솔아이원스(주)",
    "memo": "ㅌ\n매출액동결",
    "memo_updated_at": "2026-01-14T07:52:59.297675+00:00"
  },
  {
    "corp_code": "00870861",
    "company_name": "와이엠씨(주)",
    "memo": "X",
    "memo_updated_at": "2026-01-14T07:53:31.147855+00:00"
  },
  {
    "corp_code": "00612294",
    "company_name": "(주)피엔티",
    "memo": "X",
    "memo_updated_at": "2026-01-14T07:55:10.741814+00:00"
  },
  {
    "corp_code": "00899556",
    "company_name": "제룡산업(주)",
    "memo": "X",
    "memo_updated_at": "2026-01-14T07:55:50.070076+00:00"
  },
  {
    "corp_code": "00606293",
    "company_name": "(주)나이스디앤비",
    "memo": "X",
    "memo_updated_at": "2026-01-14T07:56:00.542000+00:00"
  },
  {
    "corp_code": "00608316",
    "company_name": "(주)대한과학",
    "memo": "X",
    "memo_updated_at": "2026-01-14T07:56:14.073701+00:00"
  },
  {
    "corp_code": "00664853",
    "company_name": "제이씨케미칼(주)",
    "memo": "X",
    "memo_updated_at": "2026-01-14T07:56:25.437683+00:00"
  },
  {
    "corp_code": "00657987",
    "company_name": "(주)케이엑스이노베이션",
    "memo": "X",
    "memo_updated_at": "2026-01-14T07:56:56.975812+00:00"
  },
  {
    "corp_code": "00674498",
    "company_name": "(주)골프존홀딩스",
    "memo": "X",
    "memo_updated_at": "2026-01-14T07:57:10.498229+00:00"
  },
  {
    "corp_code": "00868705",
    "company_name": "(주)윈스테크넷",
    "memo": "X",
    "memo_updated_at": "2026-01-14T07:57:17.149256+00:00"
  },
  {
    "corp_code": "00855163",
    "company_name": "미원화학(주)",
    "memo": "X",
    "memo_updated_at": "2026-01-14T08:01:36.634172+00:00"
  },
  {
    "corp_code": "00603348",
    "company_name": "(주)케이아이엔엑스",
    "memo": "X",
    "memo_updated_at": "2026-01-14T08:01:44.478872+00:00"
  },
  {
    "corp_code": "00372226",
    "company_name": "(주)티에스이",
    "memo": "X",
    "memo_updated_at": "2026-01-14T08:01:57.520290+00:00"
  },
  {
    "corp_code": "00829380",
    "company_name": "(주)피제이메탈",
    "memo": "X",
    "memo_updated_at": "2026-01-14T08:02:11.355762+00:00"
  },
  {
    "corp_code": "00194947",
    "company_name": "한전산업개발(주)",
    "memo": "X",
    "memo_updated_at": "2026-01-14T08:02:19.654731+00:00"
  },
  {
    "corp_code": "00195229",
    "company_name": "(주)미스토홀딩스",
    "memo": "X",
    "memo_updated_at": "2026-01-14T08:03:06.004359+00:00"
  },
  {
    "corp_code": "00825959",
    "company_name": "(주)하이비젼시스템",
    "memo": "X",
    "memo_updated_at": "2026-01-14T08:05:40.353649+00:00"
  },
  {
    "corp_code": "00435969",
    "company_name": "(주)인피니트헬스케어",
    "memo": "X",
    "memo_updated_at": "2026-01-14T08:05:55.110164+00:00"
  },
  {
    "corp_code": "00609324",
    "company_name": "(주)뷰웍스",
    "memo": "X",
    "memo_updated_at": "2026-01-14T08:06:15.340247+00:00"
  },
  {
    "corp_code": "00728638",
    "company_name": "한세실업(주)",
    "memo": "X",
    "memo_updated_at": "2026-01-14T08:07:57.555639+00:00"
  },
  {
    "corp_code": "00706715",
    "company_name": "미원홀딩스(주)",
    "memo": "X",
    "memo_updated_at": "2026-01-14T08:08:09.991554+00:00"
  },
  {
    "corp_code": "00397058",
    "company_name": "주식회사 엠게임",
    "memo": "X",
    "memo_updated_at": "2026-01-14T08:09:00.228904+00:00"
  },
  {
    "corp_code": "00266961",
    "company_name": "네이버(주)",
    "memo": "X",
    "memo_updated_at": "2026-01-14T08:10:40.294632+00:00"
  },
  {
    "corp_code": "00634728",
    "company_name": "(주)이크레더블",
    "memo": "X",
    "memo_updated_at": "2026-01-14T08:11:15.488955+00:00"
  },
  {
    "corp_code": "00568188",
    "company_name": "(주)마이크로컨텍솔루션",
    "memo": "X",
    "memo_updated_at": "2026-01-14T08:11:23.892141+00:00"
  },
  {
    "corp_code": "00105961",
    "company_name": "엘지이노텍(주)",
    "memo": "X",
    "memo_updated_at": "2026-01-14T08:13:35.100215+00:00"
  },
  {
    "corp_code": "00525882",
    "company_name": "(주)크레버스",
    "memo": "X",
    "memo_updated_at": "2026-01-14T08:13:45.717192+00:00"
  },
  {
    "corp_code": "00679314",
    "company_name": "(주)동성케미컬",
    "memo": "X",
    "memo_updated_at": "2026-01-14T08:14:23.214234+00:00"
  },
  {
    "corp_code": "00580065",
    "company_name": "(주)월덱스",
    "memo": "반도체\n자본집약적 산업\n소모품 \n반도체 사이클\n고객 집중도: 삼성전자·SK하이닉스 합산 약 45%\n보수적 운영\n주주친화적 스탠스 X\n\n시장가\nPER 12.4 PBR 1.2\n\n총평\n반도체 불황에서도 좋은 마진 이력,  소모품이라는 매출 구조, 미래 기술에 따른 성장 가능성 보이는 장점들을 가지고 있으나,\n보수적 운영, 주주친화적 스탠스 X, 반도체 사이클에 영향 많이 받음 등 장기적인 투자로 봤을 때 성장성이나 사이클 변동에 영향을\n받을 듯 함\nTOP 10 매수에 들어가지만 매매 조건 확실히 체크해야할듯\n\n매매\n반도체 사이클 불황 조짐\n매출액 동결 등 회사 성장 제한\n\n2026 01 26 +\nTOP 10후보 탈락\n2025 3Q 매출액 하락,\n이미 어느정도 성장한 기업인가? 라는 의심\n추후 매출액이 더 늘거나 회사 성장 가능성 보이면 다시 생각해봄\n",
    "memo_updated_at": "2026-01-26T09:05:22.791090+00:00"
  },
  {
    "corp_code": "00317681",
    "company_name": "(주)메타바이오메드",
    "memo": "ㅌ",
    "memo_updated_at": "2026-01-14T08:19:02.702688+00:00"
  },
  {
    "corp_code": "00159218",
    "company_name": "한전KPS(주)",
    "memo": "ㅌ",
    "memo_updated_at": "2026-01-14T08:22:27.003914+00:00"
  },
  {
    "corp_code": "00485177",
    "company_name": "(주)일진파워",
    "memo": "ㅌ",
    "memo_updated_at": "2026-01-14T08:22:49.270855+00:00"
  },
  {
    "corp_code": "00414850",
    "company_name": "효성아이티엑스(주)",
    "memo": "ㅌ",
    "memo_updated_at": "2026-01-14T08:23:15.370082+00:00"
  },
  {
    "corp_code": "00158963",
    "company_name": "한국유나이티드제약(주)",
    "memo": "ㅌ",
    "memo_updated_at": "2026-01-14T08:23:27.986713+00:00"
  },
  {
    "corp_code": "00533508",
    "company_name": "제이엠티(주)",
    "memo": "ㅌ",
    "memo_updated_at": "2026-01-14T08:23:45.892413+00:00"
  },
  {
    "corp_code": "00122737",
    "company_name": "팬오션(주)",
    "memo": "ㅌ",
    "memo_updated_at": "2026-01-14T08:24:33.726040+00:00"
  },
  {
    "corp_code": "00114808",
    "company_name": "동국제약(주)",
    "memo": "ㅌ",
    "memo_updated_at": "2026-01-14T08:27:01.090718+00:00"
  },
  {
    "corp_code": "00480783",
    "company_name": "상신이디피(주)",
    "memo": "ㅌ",
    "memo_updated_at": "2026-01-14T08:27:12.563743+00:00"
  },
  {
    "corp_code": "00528515",
    "company_name": "한라아이엠에스(주)",
    "memo": "ㅌ",
    "memo_updated_at": "2026-01-14T08:29:26.936955+00:00"
  },
  {
    "corp_code": "00596677",
    "company_name": "(주)매커스",
    "memo": "X\n유통, 대리점.\n성장 한계 뚜렷하다고 생각. 사업 주도권 없음",
    "memo_updated_at": "2026-01-14T20:29:31.162035+00:00"
  },
  {
    "corp_code": "00551920",
    "company_name": "(주)네오팜",
    "memo": "X\n성장률 미미",
    "memo_updated_at": "2026-01-14T20:40:56.698824+00:00"
  },
  {
    "corp_code": "00365934",
    "company_name": "(주)코세스",
    "memo": "X\n매출성장률 낮음",
    "memo_updated_at": "2026-01-14T20:42:09.169739+00:00"
  },
  {
    "corp_code": "00365457",
    "company_name": "(주)제이티",
    "memo": "X\nAC TWF",
    "memo_updated_at": "2026-01-14T20:42:25.444479+00:00"
  },
  {
    "corp_code": "00264255",
    "company_name": "(주)바텍",
    "memo": "X\n매출동결",
    "memo_updated_at": "2026-01-14T20:43:25.369637+00:00"
  },
  {
    "corp_code": "00361381",
    "company_name": "(주)제이브이엠",
    "memo": "X\n약국 약 포장 자동화\n성장 한계 있다고 생각",
    "memo_updated_at": "2026-01-14T20:45:04.025160+00:00"
  },
  {
    "corp_code": "00303217",
    "company_name": "(주)우진플라임",
    "memo": "ㅌ",
    "memo_updated_at": "2026-01-14T20:45:27.458137+00:00"
  },
  {
    "corp_code": "00219486",
    "company_name": "(주)신세계아이앤씨",
    "memo": "X\n자회사 내부 거래 기업\n수출의 대부분이 자회사에서 일어남",
    "memo_updated_at": "2026-01-14T20:49:14.048465+00:00"
  },
  {
    "corp_code": "00540863",
    "company_name": "(주)글로벌스탠다드테크놀로지",
    "memo": "O\n반도체/디스플레이 공정 인프라(환경·온도) 장비 업체 - 스크러버(80), 칠러(20)\n반도체 및 디스플레이 제조공정 등에서 사용후 배출되는 유해가스를 정화   하는 가스정화장비인 Scrubber와 \n반도체 및 디스플레이 제조 공정상 안정적인 온도유지를 제공함으로써 공정효율을 개선하는 온도조절 장비인  Chiller 제조\n\n2025 3Q 실적은 좋지 않다.\n최근 반도체 호황인데, 매출 성장이 제한된 점은 일시적 문제인지 추후 확인 필요\n-> 해당 산업은 반도체 공장에 사용하는 기계를 만드는 것이므로, 반도체 공장이 늘어날 때 매출이 늘어나는 구조입니다.\n\n사업 이해 O\n\n해자\n국내 스크러버 점유율 1등. 해자 입증 O -> 최근 경쟁자(원익)생김. 25 1Q까지 삼성에 납품되는 스크러버의 개수는 긍정적임을 확인. 추후 경쟁자의 움직임에 따른 시장 점유율 하락 조사 필요.\n-> 2025년 7월 뉴스 기준 원익 움직임 없음 확인\n\n주주친화성, 현금사용처\n굉장히 주주친화적이다. 남는 현금을 꾸준하게 CAPEX, 배당, 자사주 소각에 나눠서 쓰는 걸 확인.\nIR 자료가 홈페이지에 공개되어있어 투자자들에게 친화적인 모습을 보임.\n2025년 무상증자로 주가 접근성 개선한 이력 확인.\n\n수익성 O\n\n산업 성향\n반도체 CAPEX 사이클\n현재 2026년 반도체 호황인데, 추후 불황이 왔을 때 살아남을 수 있는지는 과거 사이클 전반에서 마진 방어력 확인된 이력 있음.\n\n매출 구조의 질\n국내 삼성, 삼성디스플레이, 하이닉스, 원익등 대기업 거래 확인.\n해외 수출비율이 높은 걸 확인(2025년 기준 56% 정도) 국내 대기업 매출에 집중되어있지 않다.\n수출액의 많은 부분이 아시아 수출쪽으로 형성되어있음.\n\n재무 안정성\n부채 비율 낮음\n\n경영진\n최근 2025년 3월 대표 이사 변경됨.\n경영진 지분율은 적당 (20%대)\n\n현재 시장가가 비싸지 않은 점 (PER 11, PBR 1.8)\n\n이 기업이 현재 수준의 수익성을 10년간 유지할 수 있는가?\n-> 반도체 불황이 왔을 때 일시적 흔들림 예상. 하지만 과거 불황 때 방어 마진 있어서 결국 성장할 것이라 생각됩니다.\n\nTOP 10 후보 선정\n\n2026 01 26 +\nTOP 10 후보 탈락\n2025 3Q 매출액 동결 && 2021 ~ 2024 매출액 CAGR 동결 등 성장에 한계가 왔나 ? 의심이 든다\n회사 성장 여지가 다시 보이면 매수 고려",
    "memo_updated_at": "2026-01-26T09:06:44.154651+00:00"
  },
  {
    "corp_code": "00531014",
    "company_name": "(주)유진테크",
    "memo": "X\n더 매력적인 반도체 기업이 있다고 생각",
    "memo_updated_at": "2026-01-14T22:05:54.688223+00:00"
  },
  {
    "corp_code": "00360595",
    "company_name": "현대글로비스(주)",
    "memo": "X\n현대그룹 인프라를 위한 기업 -> 투자자의 이윤 추구와 가치 상충\n",
    "memo_updated_at": "2026-01-14T23:51:45.322341+00:00"
  },
  {
    "corp_code": "00190756",
    "company_name": "(주)와이엔텍",
    "memo": "ㅌ",
    "memo_updated_at": "2026-01-14T23:52:44.762627+00:00"
  },
  {
    "corp_code": "00113225",
    "company_name": "대한제강(주)",
    "memo": "ㅌ",
    "memo_updated_at": "2026-01-14T23:54:03.712722+00:00"
  },
  {
    "corp_code": "00506294",
    "company_name": "(주)가비아",
    "memo": "X\n클라우드, 서비스형 소프트웨어(SaaS), 보안, IDE\n이미 충분히 성장했다고 판단, 기업 시장 가치 판단에 비해 성장세는 한계가 있다고 생각\n-> 이미 클라우드는 외국 기업들 점유율이 높고, 국내 기업들이 경쟁 자체를 생각할 수 없다고 생각\n결국 내수(해당 기업도 내수쪽 공공기관 사업, 민간사업 등)인데, 한계 있다고 생각\n같은 이유로 케이아이엔엑스(가비아가 최대 주주로써 기업 운영 영향력 끼침)도 패스",
    "memo_updated_at": "2026-01-15T01:01:16.645354+00:00"
  },
  {
    "corp_code": "00161383",
    "company_name": "한미반도체(주)",
    "memo": "X\nX\n반도체 후공정 -> 불량률을 최소화 하는  TC 본딩 전후공정의 필수 장비\n판매 기업 삼성, 하이닉스등 대기업 확인\n힘들 때 버티고 호황올 때 수출이 대폭으로 느는 반도체 사이클 기업\n특이한점은 남는 자금을 투자에 쓰는 듯? 투자 수익이 오락가락함 (2023년 당기순이익도 투자로 인한 순이익)\n하지만 시장가가 너무 비싸서 매수 X",
    "memo_updated_at": "2026-01-15T01:39:41.337936+00:00"
  },
  {
    "corp_code": "00447487",
    "company_name": "(주)제주반도체",
    "memo": "X\n반도체쪽 매력적인 선택지가 더 많음",
    "memo_updated_at": "2026-01-15T01:42:45.377020+00:00"
  },
  {
    "corp_code": "00178790",
    "company_name": "동양이엔피(주)",
    "memo": "ㅌ",
    "memo_updated_at": "2026-01-15T01:43:34.406322+00:00"
  },
  {
    "corp_code": "00328191",
    "company_name": "(주)케이에스피",
    "memo": "X\n선박 추진용 엔진 부품\n홈페이지 누락 등 기업 정보 제한적",
    "memo_updated_at": "2026-01-15T10:56:35.831836+00:00"
  },
  {
    "corp_code": "00159786",
    "company_name": "(주)유니드",
    "memo": "X\n화학 원재료\n1. 제품 차별화 없음\n2. 중국쪽 수출액이 높은편인데, 중국 정책 변화로 인한 장기 마진 예측 불가.",
    "memo_updated_at": "2026-01-15T11:08:20.763638+00:00"
  },
  {
    "corp_code": "00414601",
    "company_name": "유니퀘스트(주)",
    "memo": "x",
    "memo_updated_at": "2026-01-15T11:09:06.942345+00:00"
  },
  {
    "corp_code": "00488989",
    "company_name": "한양디지텍(주)",
    "memo": "X\nDARM 반도체\n1. DARM은 완전한 커머디티 제품\n2. 매출원가 제어성 부족\n3. 최근 반도체 호황임에도 불구하고 매출액이 늘지 않았다.\n\n",
    "memo_updated_at": "2026-01-15T11:19:39.254722+00:00"
  },
  {
    "corp_code": "00399694",
    "company_name": "(주)숲",
    "memo": "X\n성장 한계가 내수로 명확하다고 생각합니다",
    "memo_updated_at": "2026-01-15T11:24:12.365850+00:00"
  },
  {
    "corp_code": "00468374",
    "company_name": "(주)원익큐엔씨",
    "memo": "X\n다른 반도체 기업이 더 매력적이라고 판단",
    "memo_updated_at": "2026-01-15T11:27:34.672338+00:00"
  },
  {
    "corp_code": "00398808",
    "company_name": "(주)디지털대성",
    "memo": "X\n교육",
    "memo_updated_at": "2026-01-15T11:27:59.396766+00:00"
  },
  {
    "corp_code": "00107613",
    "company_name": "(주)이수페타시스",
    "memo": "O\nPCB\n1. 경기불황기를 이겨내고 꾸준한 성장률 \n2. PCB 사업에서 좋은 영업이익률\n3. 18층 이상 고다층 PCB 제조사 (PCB는 경쟁률이 높은데, 층의 개수가 기술력을 뜻함.) 글로벌에서도 경쟁력 있음을 확인\n\n근데 시장가가 비싸다 이미 프리미엄이 많이 붙음 PER 60배\n+ 구조적 CAPEX 투자 산업인데, 2022, 2023 FCF 음수 -> CAPEX 투자 -> 이후 3~4년동안 실수 없이 쭉 성장하지 못한다면 흔들릴 가능성 있다.\n\n기업은 사고 싶다\n시장가는 안 사고 싶다\n기다린다\n\n\n",
    "memo_updated_at": "2026-01-15T11:55:33.304565+00:00"
  },
  {
    "corp_code": "00245472",
    "company_name": "(주)티씨케이",
    "memo": "좋기좋못시 -> 관찰\n반도체 소자생성용 소재를 공급하는 반도체 재료산업\n소자생성때 사용되는 공정용 소모품을 판매 (고순도 흑연 제품)\n\n\n소모성 부품, CAPEX 의존성이 낮다.\n필수 + 소모품 조합이 좋은 조건이라고 생각함 -> 실제로 영업이익률이 높다.\n\n흑연,SIC 원재료 리스크 존재\n현재 원재료는 모 회사로부터 엔화로 수입하고 있음.\n\n사업 이해\n반도체 소자생성용 소재를 공급하는 반도체 재료산업\n소자생성때 사용되는 공정용 소모품을 판매 (고순도 흑연 제품)\n\n해자\n대형 FAB에 지속적 납품 (공식적인 기재는 없으나, IR에 대형사 FAB에 지속적 납품이라고 기재되어있고, 매출액을 보아 웬만하면 납품하지 않을까 추정)\n공정 신뢰성 + 인증\n니치하지만 핵심 공정 포지션\n-> 락인\n\n주주친화성\n배당 비율이 높은 편 (2025년 IR 공시는 22%, 대략 20% 정도)\n최근 (2024년) 한 해 자사주 소각 2회 진행\n반도체 불황이었던 2023년에 현금이 부족함에도 불구하고 회사의 자금을 이용해 배당, CAPEX를 진행함.\n유상증자 진행 X\n\n산업 성향\n반도체 제조 사이클\n\n매출 구조의 질\n대형 FAB에 지속적 납품\n소모품이라 사이클 때 꾸준한 수익 발생\n\n재무 안정성\n부채 비율 매우 낮다\n\n경영진\n모 회사는 일본 회사임.\n최근(2024) 전 삼성전자 상무,자문을 맡았던 오창민을 사장으로 영입함.\n\n경영진\n모 회사 TOCAI CARBON의 지분율 50%\n\n최근 동향\n2022년, 2023년 공장 증설로 인한 CAPEX 증가에 따른 추후 감가 상각, 매출 증가율 체크 요망.\n\n이 기업이 현재 수준의 수익성을 10년간 유지할 수 있는가?\n탄탄하다고 생각합니다.\n\n현재 시장가는 PER 26.8, PBR 3.6으로 좀 비싼편\n기업은 좋으나, 시장가가 좀 비싸다고 판단.\n또한 모 회사가 일본이라는점도 좀 걸린다. (웬만하면 국장을 한 만큼 한국기업에 투자하고 싶은 개인적인 감정) \n-> 감정이기때문에 좋은 가격이 돌아온다면 매수 생각 있음\n\n토스 분류 좋기좋못시(상)에 넣고 관찰 대상. 가격이 낮아지면 매수",
    "memo_updated_at": "2026-01-20T23:50:41.793832+00:00"
  },
  {
    "corp_code": "00160010",
    "company_name": "(주)한국큐빅",
    "memo": "X\n매출 원가가 너무 높아 영업이익률이 낮다",
    "memo_updated_at": "2026-01-15T21:08:28.131838+00:00"
  },
  {
    "corp_code": "00264547",
    "company_name": "(주)케이지이니시스",
    "memo": "X\n연결기업들의 사업들이 너무 짬뽕.\n가장 대표 기업은 1차 필터를 넘기지 못해 패스함.",
    "memo_updated_at": "2026-01-15T21:12:46.455049+00:00"
  },
  {
    "corp_code": "00426086",
    "company_name": "티케이지휴켐스(주)",
    "memo": "X\n정밀화학분야 중간소재 제조업\n국내 질산 점유율 높음\n사업 기반은 탄탄하지만, 사이클주라는 점\n현재 화학분야 시장 PER이 전체적으로 낮은 편\n타 화학분야에서 더 좋은 기업이 있을 수 있으니 일단 대기\n\n추가 : 범용화학부분은 체크리스트가 많다. 특수화학쪽에 투자 권함.\n",
    "memo_updated_at": "2026-01-15T22:13:01.646907+00:00"
  },
  {
    "corp_code": "00155258",
    "company_name": "포스코스틸리온(주)",
    "memo": "X\n강판\n경쟁률 치열 -> 영업이익률에서 보임\n가격결정력 약함, 산업 사이클에 영향 받음",
    "memo_updated_at": "2026-01-15T22:15:11.238123+00:00"
  },
  {
    "corp_code": "00355089",
    "company_name": "(주)토탈소프트뱅크",
    "memo": "X",
    "memo_updated_at": "2026-01-25T06:20:12.600028+00:00"
  },
  {
    "corp_code": "00389110",
    "company_name": "(주)지어소프트",
    "memo": "X\nIT + 유통\nIT 소프트웨어 (기업 관리) 판매,\n내부적으로 농축산물 직판매 유통 + 유통에 필요한 홈페이지등을 스스로 만들어서 운영중인 기업\n저마진\n꾸준한 성장\nCAPEX, 부채 비율 낮음\n",
    "memo_updated_at": "2026-01-25T06:24:58.740107+00:00"
  },
  {
    "corp_code": "00246620",
    "company_name": "(주)케이엘넷",
    "memo": "X\n매출액동결",
    "memo_updated_at": "2026-01-15T23:08:41.341699+00:00"
  },
  {
    "corp_code": "00298340",
    "company_name": "(주)에스티아이",
    "memo": "X\n반도체 공정\n반도체 호황에 맞는 수익 곡선을 그리고 있으나,\n구조적으로 CAPEX가 높으며, 영업이익률이 낮아 성장속도의 문제가 있을것이라고 생각됨.",
    "memo_updated_at": "2026-01-19T21:24:31.291235+00:00"
  },
  {
    "corp_code": "00156956",
    "company_name": "한국기업평가(주)",
    "memo": "ㅌ",
    "memo_updated_at": "2026-01-19T21:26:00.312623+00:00"
  },
  {
    "corp_code": "00360036",
    "company_name": "(주)백금티앤에이",
    "memo": "ㅌ",
    "memo_updated_at": "2026-01-19T21:26:07.335851+00:00"
  },
  {
    "corp_code": "00178851",
    "company_name": "(주)동양에스텍",
    "memo": "ㅌ",
    "memo_updated_at": "2026-01-19T21:26:23.401976+00:00"
  },
  {
    "corp_code": "00336297",
    "company_name": "고려신용정보(주)",
    "memo": "ㅌ",
    "memo_updated_at": "2026-01-19T21:26:29.495904+00:00"
  },
  {
    "corp_code": "00144650",
    "company_name": "(주)유신",
    "memo": "ㅌ\n영업이익률 너무 낮음",
    "memo_updated_at": "2026-01-19T21:28:51.955993+00:00"
  },
  {
    "corp_code": "00303396",
    "company_name": "한국컴퓨터(주)",
    "memo": "x\n영업이익률이 너무 낮음",
    "memo_updated_at": "2026-01-19T21:32:43.747717+00:00"
  },
  {
    "corp_code": "00352499",
    "company_name": "(주)링네트",
    "memo": "ㅌ",
    "memo_updated_at": "2026-01-19T21:33:08.843587+00:00"
  },
  {
    "corp_code": "00357740",
    "company_name": "엔에이치엔케이씨피 주식회사",
    "memo": "ㅌ",
    "memo_updated_at": "2026-01-19T21:33:28.031641+00:00"
  },
  {
    "corp_code": "00141608",
    "company_name": "(주)오리엔탈정공",
    "memo": "x\n딱히 투자할만한 메리트를 못 느낌",
    "memo_updated_at": "2026-01-19T21:38:00.864798+00:00"
  },
  {
    "corp_code": "00369657",
    "company_name": "리노공업(주)",
    "memo": "O\n\n당사는 전량 수입에 의존하던 검사용 PROBE(SPRING CONTACT PROBE:LEENO PIN, 27%)와 \n반도체 검사용 소켓(IC TEST SOCKET, 61%)을 자체브랜드로 개발하여 제조 및 판매하는 사업과 \n초음파 진단기 등에 적용되는 의료기기 부품을 제조 및 판매하는사업(10%) 등을 영위하고 있습니다.\n\n사업 이해 O\n\n해자\n경쟁력 글로벌 최상위권\n반도체 공정 필수 기술\n국내, 해외 대형사에 납품중(2025 IR 자료 출처)\n-> 락인 구조\n\n주주친화성\n최근 3년(2024,2023,2022) FCF의 절반 정도의 금액을 배당한 이력이 있음.\n유상증자X\n\n산업 성향\n반도체 사이클 산업 (소모품,  소모품검사의 장비 등)\n\n매출 구조의 질\n글로벌 탑의 기술을 가진 만큼 국내, 해외의 대기업에게 납품 중.\n강한 마진력을 봤을 때 고부가가치 산업 + 가격 결정권에 긍정적 신호로 판단.\n\n재무 안정성\n부채 거의 없음\n\n경영진\n최대 주주의 지분율 약 35%\n\n특이사항\n2023년 capa증가를 위한 공장 신설. -> 추후 매출액 변화량 지켜 볼 필요성 있음. -> 2025 3Q 기준 매출액 괴물같이 증가\n2025 3Q 매출액 YOY 약 50% 상승\n\n현재 가격 PER 32.1 PBR 7.0\n\n이 기업이 현재 수준의 수익성을 10년간 유지할 수 있는가?\n보통놈이 아닙니다\n\n최종 의견\nTOP 10 후보\n가격이 굉장히 비싸지만, 반도체 불황시 마진 방어 이력 + 미친 고마진 구조 + 글로벌에서 해자 입증.\n최근 반도체 호황 때 매출액 증가율 YOY 50% -> 물 들어올 때 노가 아니라 엔진급 출력\n\n2026 01 26\nTOP 10 매수 후보 제외\n엄청난 지표들을 보유하고, 단단한 깅버이지만, 생각됐던 단점인 이미 충분한 성장을 한 기업이라는 생각이 듦.\n다른 강한 성장세를 보여주는 기업이 있다고 판단되어 제외.",
    "memo_updated_at": "2026-01-26T09:48:36.496959+00:00"
  },
  {
    "corp_code": "00349732",
    "company_name": "코나아이(주)",
    "memo": "X",
    "memo_updated_at": "2026-01-25T21:41:35.647590+00:00"
  },
  {
    "corp_code": "00261009",
    "company_name": "감성코퍼레이션(주)",
    "memo": "사업 이해 O\n어패럴\n\n해자 X\n해자력 약함 -> 어패럴 산업은 경쟁자가 매우 많다\n\n주주친화성 O\n재고를 미리 쌓아두는 산업 특성상 현금유동이 부족한데, 그걸 유상증자로 해결\n-> 하지만 자사주 소각을 지속적으로 진행하는 중\n\n부채 안정성 O\n\n시장가 PER 17.2 PBR 4.5\n\n총평 \n성장주, 2024년 재고를 많이 쌓아놓고 2025년 매출액 YOY 대비 증가 확인 -> 지속적 성장 확인\n자본대비 효율과 영업이익률 좋고 2020년, 2021년 코로나 사태때 무너지지 않고 버틴 이력은 + 포인트\n좀 비싸긴 한데 높은 성장률과 사업의 방향성도 더 성장하려는 의지와 그에 따른 실적도 확인되어 TOP 10 후보 추가\n\n매매 포인트\n매출 실적 감소, 그에 따른 판관비로 매출을 늘리려는 행보가 보일 시 \n\n2026 01 26 x\nTOP 10 후보 탈락\n타 기업이 더 매력적이라고 판단됨\n",
    "memo_updated_at": "2026-01-26T09:45:38.906044+00:00"
  },
  {
    "corp_code": "00219848",
    "company_name": "(주)서희건설",
    "memo": "X\n상장폐지경고, 거래정지",
    "memo_updated_at": "2026-01-19T22:55:09.276402+00:00"
  },
  {
    "corp_code": "00252135",
    "company_name": "주성엔지니어링(주)",
    "memo": "x",
    "memo_updated_at": "2026-01-19T22:56:05.071077+00:00"
  },
  {
    "corp_code": "00118804",
    "company_name": "(주)동진쎄미켐",
    "memo": "X\n",
    "memo_updated_at": "2026-01-25T20:16:50.612199+00:00"
  },
  {
    "corp_code": "00128315",
    "company_name": "삼지전자(주)",
    "memo": "X",
    "memo_updated_at": "2026-01-25T06:21:05.229107+00:00"
  },
  {
    "corp_code": "00260569",
    "company_name": "유니셈(주)",
    "memo": "ㅌ",
    "memo_updated_at": "2026-01-19T23:19:56.521648+00:00"
  },
  {
    "corp_code": "00244455",
    "company_name": "(주)케이티앤지",
    "memo": "x\n담배는 사회에 해롭다",
    "memo_updated_at": "2026-01-19T23:20:16.915619+00:00"
  },
  {
    "corp_code": "00122551",
    "company_name": "(주)백산",
    "memo": "NIKE, ADIDAS, REEBOK 등 국제적으로 인지도가 높은 회사에 대한 공급이 매출액의 80%이상을 차지하고 있습니다.\n\n사업 이해 O\n폴리우레탄 합성피혁 (인조가죽)\n\n해자\n기술력 해자는 약한편\n세계적인 브랜드에게 장기 납품 -> 신뢰, 전환 가능성 낮아보임\n세계적인 브랜드인 NIKE, ADIDAS, REEBOK의 합성피혁 사용량 25%를 점유하고 있음\n(출처 : 2024 백산 사업보고서)\n\n주주친화성\n주기적으로 자사주 소각, 자사주 매입 진행 중\n\n재무 안정성 O\n\n경영진\n대표와 그 관계자가 가지고 있는 주식 비율 57%\n\n시장가 PER 6 PBR 1\n\n최종 판단\n잔잔한 기업\n나쁜 기업은 아니나 장기적으로 들고 갈 메리트가 부족해보임",
    "memo_updated_at": "2026-01-25T06:09:56.230954+00:00"
  },
  {
    "corp_code": "00219361",
    "company_name": "해성산업(주)",
    "memo": "ㅌ",
    "memo_updated_at": "2026-01-19T23:33:55.033711+00:00"
  },
  {
    "corp_code": "00148276",
    "company_name": "(주)제일기획",
    "memo": "X\n안정적 배당주",
    "memo_updated_at": "2026-01-19T23:38:25.154205+00:00"
  },
  {
    "corp_code": "00231105",
    "company_name": "(주)동성화인텍",
    "memo": "LNG선 극저온 보냉재 \n\n기술 자체 진입장벽 높고 해당 산업 국내 점유율 60%\n-> 해자력 최상\n\n주주친화성\n과거 CB 전환으로 주식 수 증가(희석 이력 존재)\n최근 유상증자 없음\n배당 비율도 적은편 공격적 주주환원 성향은 아니다.\n\n사이클 영향 크다.\nLNG, 친환경 선박이므로 중장기 성장 산업의 경향도 보임.\n\n매출 구조의 질 좋은 편 (기술, 인증으로 협상력 높고, 매출처가 글로벌 대형 조선사 중심임)\n\n재무 안정성 O\n\n시장가 \nPER 13.2 PBR 3.3\n\n특이사항\n2025 3Q 매출액 YOY대비 증가 확인\n\n총평\nTOP 10 후보\n해자가 높고 성장세가 좋으며, 조선주 사이클이 오기 전 저점 매수 구간이라고 생각됨\n\n매매\n조선업 수주가 줄어들어 매출액이 감소했다는 자료 발견할 시 \n\n2026 01 26 +\nLNG선 과거 수주와 최근 수주 비교해 감소 확인\n주가 현재가 최상점 + 슬슬 떨어질 것 이라고 판단되어 후보 탈락\n",
    "memo_updated_at": "2026-01-26T08:52:37.070442+00:00"
  },
  {
    "corp_code": "00155948",
    "company_name": "로젠(주)",
    "memo": "X\n유통\n마진 적음",
    "memo_updated_at": "2026-01-20T00:04:57.975709+00:00"
  },
  {
    "corp_code": "00144164",
    "company_name": "SK가스(주)",
    "memo": "ㅌ",
    "memo_updated_at": "2026-01-20T00:06:13.494852+00:00"
  },
  {
    "corp_code": "00208444",
    "company_name": "피에스케이홀딩스(주)",
    "memo": "X\n지주회사",
    "memo_updated_at": "2026-01-20T00:16:48.742195+00:00"
  },
  {
    "corp_code": "00126308",
    "company_name": "삼성이앤에이(주)",
    "memo": "X\n산업 이해가 어렵다",
    "memo_updated_at": "2026-01-20T00:27:54.686447+00:00"
  },
  {
    "corp_code": "00115065",
    "company_name": "(주)동남합성",
    "memo": "ㅌ",
    "memo_updated_at": "2026-01-20T00:28:02.482189+00:00"
  },
  {
    "corp_code": "00133876",
    "company_name": "(주)세보엠이씨",
    "memo": "ㅌ",
    "memo_updated_at": "2026-01-20T00:28:18.307373+00:00"
  },
  {
    "corp_code": "00164724",
    "company_name": "현대엘리베이터(주)",
    "memo": "ㅌ",
    "memo_updated_at": "2026-01-20T00:29:56.709878+00:00"
  },
  {
    "corp_code": "00102432",
    "company_name": "계룡건설산업(주)",
    "memo": "ㅌ",
    "memo_updated_at": "2026-01-20T00:30:08.071122+00:00"
  },
  {
    "corp_code": "00158501",
    "company_name": "(주)에스원",
    "memo": "ㅌ",
    "memo_updated_at": "2026-01-20T00:30:26.889042+00:00"
  },
  {
    "corp_code": "00164645",
    "company_name": "에이치엠엠(주) ",
    "memo": "X\n사이클인데 이해도 낮음",
    "memo_updated_at": "2026-01-20T00:46:51.313233+00:00"
  },
  {
    "corp_code": "00113128",
    "company_name": "대한약품공업(주)",
    "memo": "X\n배당주 느낌인데 거래량이 너무 적음",
    "memo_updated_at": "2026-01-20T00:58:15.636045+00:00"
  },
  {
    "corp_code": "00150165",
    "company_name": "(주)브이티",
    "memo": "O\n화장품\n리들샷 유행이었다가 현재 지나갓다?\n자세히 조사 필요할듯",
    "memo_updated_at": "2026-01-20T01:35:07.222905+00:00"
  },
  {
    "corp_code": "00161116",
    "company_name": "에이치엘디앤아이한라(주)",
    "memo": "ㅌ",
    "memo_updated_at": "2026-01-20T01:10:11.207120+00:00"
  },
  {
    "corp_code": "00121154",
    "company_name": "(주)엠에스씨",
    "memo": "X\n식품산업 고수익 내기 어려워보임",
    "memo_updated_at": "2026-01-20T01:16:17.397020+00:00"
  },
  {
    "corp_code": "00101488",
    "company_name": "(주)경동나비엔",
    "memo": "X",
    "memo_updated_at": "2026-01-25T06:24:05.776311+00:00"
  },
  {
    "corp_code": "00161462",
    "company_name": "(주)에이티넘인베스트먼트",
    "memo": "ㅌ",
    "memo_updated_at": "2026-01-20T01:40:16.985026+00:00"
  },
  {
    "corp_code": "00124090",
    "company_name": "(주)한국특강",
    "memo": "ㅌ",
    "memo_updated_at": "2026-01-20T01:41:41.764950+00:00"
  },
  {
    "corp_code": "00140946",
    "company_name": "한솔로지스틱스(주)",
    "memo": "x",
    "memo_updated_at": "2026-01-20T01:44:28.502139+00:00"
  },
  {
    "corp_code": "00160375",
    "company_name": "진양폴리우레탄(주)",
    "memo": "x",
    "memo_updated_at": "2026-01-20T01:45:03.819708+00:00"
  },
  {
    "corp_code": "00122056",
    "company_name": "미창석유공업(주)",
    "memo": "x",
    "memo_updated_at": "2026-01-20T01:45:16.448315+00:00"
  },
  {
    "corp_code": "00121932",
    "company_name": "미원상사(주)",
    "memo": "x",
    "memo_updated_at": "2026-01-20T01:49:50.510590+00:00"
  },
  {
    "corp_code": "00101220",
    "company_name": "KG케미칼(주)",
    "memo": "x",
    "memo_updated_at": "2026-01-20T02:02:34.335343+00:00"
  },
  {
    "corp_code": "00112679",
    "company_name": "대창단조(주)",
    "memo": "x",
    "memo_updated_at": "2026-01-20T02:02:56.644904+00:00"
  },
  {
    "corp_code": "00140955",
    "company_name": "(주)한솔케미칼",
    "memo": "x",
    "memo_updated_at": "2026-01-20T02:13:32.976561+00:00"
  },
  {
    "corp_code": "00118026",
    "company_name": "동원산업(주)",
    "memo": "x",
    "memo_updated_at": "2026-01-20T02:14:30.776747+00:00"
  },
  {
    "corp_code": "00125521",
    "company_name": "에스엘(주)",
    "memo": "x\ncapex + 사이클 리스크 비해 성장하기 어려워보임",
    "memo_updated_at": "2026-01-20T02:23:42.505960+00:00"
  },
  {
    "corp_code": "00140964",
    "company_name": "(주)영원무역홀딩스",
    "memo": "ㅌ",
    "memo_updated_at": "2026-01-20T02:23:58.843285+00:00"
  },
  {
    "corp_code": "00172291",
    "company_name": "(주)더존비즈온",
    "memo": "ㅌ\n너무 비싸",
    "memo_updated_at": "2026-01-20T02:26:07.483132+00:00"
  },
  {
    "corp_code": "00116949",
    "company_name": "(주)디엔오토모티브",
    "memo": "x",
    "memo_updated_at": "2026-01-20T02:44:12.819392+00:00"
  },
  {
    "corp_code": "00158149",
    "company_name": "한국쉘석유(주)",
    "memo": "X",
    "memo_updated_at": "2026-01-25T05:49:18.022348+00:00"
  },
  {
    "corp_code": "00128412",
    "company_name": "삼진제약(주)",
    "memo": "ㅌ",
    "memo_updated_at": "2026-01-20T03:00:09.341291+00:00"
  },
  {
    "corp_code": "00106368",
    "company_name": "금호석유화학(주)",
    "memo": "ㅌ",
    "memo_updated_at": "2026-01-20T03:00:24.409530+00:00"
  },
  {
    "corp_code": "00160418",
    "company_name": "한국무브넥스(주)",
    "memo": "ㅌ",
    "memo_updated_at": "2026-01-20T03:03:40.363289+00:00"
  },
  {
    "corp_code": "00126566",
    "company_name": "한화에어로스페이스(주)",
    "memo": "방산",
    "memo_updated_at": "2026-01-08T21:39:45.023617+00:00"
  },
  {
    "corp_code": "00129271",
    "company_name": "삼화전기(주)",
    "memo": "ㅌ",
    "memo_updated_at": "2026-01-20T03:05:13.033033+00:00"
  },
  {
    "corp_code": "00115676",
    "company_name": "KG스틸(주)",
    "memo": "ㅌ",
    "memo_updated_at": "2026-01-20T03:06:28.121551+00:00"
  },
  {
    "corp_code": "00148896",
    "company_name": "오씨아이홀딩스 주식회사",
    "memo": "ㅌ",
    "memo_updated_at": "2026-01-20T03:06:36.419152+00:00"
  },
  {
    "corp_code": "00126487",
    "company_name": "주식회사 에프앤에프홀딩스",
    "memo": "ㅌ",
    "memo_updated_at": "2026-01-20T03:11:47.269057+00:00"
  },
  {
    "corp_code": "00164812",
    "company_name": "현대코퍼레이션(주)",
    "memo": "x",
    "memo_updated_at": "2026-01-20T03:16:24.510524+00:00"
  },
  {
    "corp_code": "00150828",
    "company_name": "진흥기업(주)",
    "memo": "x",
    "memo_updated_at": "2026-01-20T03:17:45.114545+00:00"
  },
  {
    "corp_code": "00107066",
    "company_name": "남광토건(주)",
    "memo": "x",
    "memo_updated_at": "2026-01-20T03:17:59.612798+00:00"
  },
  {
    "corp_code": "00109718",
    "company_name": "(주)사조대림",
    "memo": "x",
    "memo_updated_at": "2026-01-20T03:21:23.551541+00:00"
  },
  {
    "corp_code": "00127255",
    "company_name": "(주)삼영",
    "memo": "x",
    "memo_updated_at": "2026-01-20T03:21:31.209304+00:00"
  },
  {
    "corp_code": "00129350",
    "company_name": "삼화콘덴서공업(주)",
    "memo": "x",
    "memo_updated_at": "2026-01-20T03:21:38.418319+00:00"
  },
  {
    "corp_code": "00157681",
    "company_name": "롯데정밀화학(주)",
    "memo": "x",
    "memo_updated_at": "2026-01-20T03:21:45.190962+00:00"
  },
  {
    "corp_code": "00120076",
    "company_name": "(주)LX인터내셔널",
    "memo": "x",
    "memo_updated_at": "2026-01-20T03:22:02.457487+00:00"
  },
  {
    "corp_code": "00160843",
    "company_name": "주식회사 DB하이텍",
    "memo": "x\n파운드리는 시스템 반도체를 위탁 생산하는 사업\n다른 반도체 기업이 더 투자하기 좋다고 생각\n최근 시장가 과열",
    "memo_updated_at": "2026-01-21T01:10:42.109232+00:00"
  },
  {
    "corp_code": "00126955",
    "company_name": "삼양식품(주)",
    "memo": "X\n불닭 의존성이 좀 높다.\n최근 CAPEX 재투자 크게 했음",
    "memo_updated_at": "2026-01-20T03:39:04.304902+00:00"
  },
  {
    "corp_code": "00152862",
    "company_name": "(주)코오롱",
    "memo": "ㅌ",
    "memo_updated_at": "2026-01-20T03:39:32.897639+00:00"
  },
  {
    "corp_code": "00125530",
    "company_name": "(주)SPC삼립",
    "memo": "ㅌ",
    "memo_updated_at": "2026-01-20T03:40:25.020246+00:00"
  },
  {
    "corp_code": "00106641",
    "company_name": "기아(주)",
    "memo": "X",
    "memo_updated_at": "2026-01-25T20:59:25.667394+00:00"
  },
  {
    "corp_code": "00117230",
    "company_name": "주식회사 티와이엠",
    "memo": "ㅌ",
    "memo_updated_at": "2026-01-20T03:45:13.309914+00:00"
  },
  {
    "corp_code": "00159102",
    "company_name": "DB손해보험(주)",
    "memo": "x",
    "memo_updated_at": "2026-01-20T03:52:09.708677+00:00"
  },
  {
    "corp_code": "00150439",
    "company_name": "진양산업(주)",
    "memo": "x",
    "memo_updated_at": "2026-01-20T03:52:54.037992+00:00"
  },
  {
    "corp_code": "00124197",
    "company_name": "(주)세아제강지주",
    "memo": "x",
    "memo_updated_at": "2026-01-20T03:53:03.148145+00:00"
  },
  {
    "corp_code": "00113526",
    "company_name": "(주)대한항공",
    "memo": "x",
    "memo_updated_at": "2026-01-20T03:54:18.118404+00:00"
  }
]